Pacman_FPGA/source/clock_div.sv
module clock_div (
    input logic clk,
    input logic rst,
    output logic clk_div
);

    logic [18:0] count;

    always_ff @(posedge clk or posedge rst) begin
        if (rst) begin
            count <= '0;
            clk_div <= 1'b0;
        end else begin
            if (count == 19'd418749) begin // returns 60 Hz
                count <= '0;
                clk_div <= 1'b1;
            end else begin
                count <= count + 1'b1;
                clk_div <= 1'b0;
            end
        end
    end

endmodule

Pacman_FPGA/testbench/clock_div_tb.sv
`timescale 1ns/1ps

module clock_div_tb;

    logic clk;
    logic rst;
    logic clk_div;

    int pass_count;
    int fail_count;

    clock_div dut (
        .clk(clk),
        .rst(rst),
        .clk_div(clk_div)
    );

    initial clk = 1'b0;
    always #5 clk = ~clk;

    task automatic check(input string name, input logic cond);
        if (cond) begin
            pass_count++;
            $display("PASS: %s", name);
        end else begin
            fail_count++;
            $display("FAIL: %s (clk_div=%b)", name, clk_div);
        end
    endtask

    task automatic tick(input int n = 1);
        repeat (n) @(posedge clk);
    endtask

    // Plant count just before the terminal value, then let the DUT advance.
    task automatic arm_near_terminal;
        @(negedge clk);
        force dut.count = 19'd418748;
        @(posedge clk);
        release dut.count;
    endtask

    initial begin
        pass_count = 0;
        fail_count = 0;
        rst        = 1'b1;

        $dumpfile("waves/clock_div.vcd");
        $dumpvars(0, clock_div_tb);

        tick(2);
        check("async reset clears pulse", clk_div === 1'b0);
        rst = 1'b0;
        tick(5);
        check("idle stays low", clk_div === 1'b0);

        arm_near_terminal();
        #1;
        check("count now 418749, pulse still low", clk_div === 1'b0);
        tick(1);
        #1;
        check("terminal count pulses high", clk_div === 1'b1);
        tick(1);
        #1;
        check("pulse is single-cycle", clk_div === 1'b0);

        arm_near_terminal();
        tick(1);
        #1;
        check("second pulse high", clk_div === 1'b1);
        tick(1);
        #1;
        check("second pulse clears", clk_div === 1'b0);

        rst = 1'b1;
        #1;
        check("async reset mid-run", clk_div === 1'b0);

        $display("\nclock_div_tb: %0d PASS, %0d FAIL", pass_count, fail_count);
        if (fail_count != 0) $fatal(1);
        $finish;
    end

endmodule

Pacman_FPGA/waves/clock_div.vcd
$date
	Sat Aug  1 22:09:53 2026
$end
$version
	Icarus Verilog
$end
$timescale
	1ps
$end
$scope module clock_div_tb $end
$var wire 1 ! clk_div $end
$var reg 1 " clk $end
$var reg 1 # rst $end
$var integer 32 $ fail_count [31:0] $end
$var integer 32 % pass_count [31:0] $end
$scope module dut $end
$var wire 1 " clk $end
$var wire 1 # rst $end
$var reg 1 ! clk_div $end
$var reg 19 & count [18:0] $end
$upscope $end
$scope task arm_near_terminal $end
$upscope $end
$scope task check $end
$upscope $end
$scope task tick $end
$upscope $end
$upscope $end
$enddefinitions $end
$comment Show the parameter values. $end
$dumpall
$end
#0
$dumpvars
b0 &
b0 %
b0 $
1#
0"
0!
$end
#5000
1"
#10000
0"
#15000
b1 &
0#
b1 %
1"
#20000
0"
#25000
b10 &
1"
#30000
0"
#35000
b11 &
1"
#40000
0"
#45000
b100 &
1"
#50000
0"
#55000
b101 &
1"
#60000
0"
#65000
b110 &
b10 %
1"
#70000
b1100110001110111100 &
0"
#75000
b1100110001110111101 &
1"
#76000
b11 %
#80000
0"
#85000
1!
b0 &
1"
#86000
b100 %
#90000
0"
#95000
0!
b1 &
1"
#96000
b101 %
#100000
b1100110001110111100 &
0"
#105000
b1100110001110111101 &
1"
#110000
0"
#115000
1!
b0 &
1"
#116000
b110 %
#120000
0"
#125000
0!
b1 &
1"
#126000
b0 &
1#
b111 %
#127000
b1000 %
