Pacman_FPGA/source/game_fsm.sv
module game_fsm (
    input  logic       clk,
    input  logic       reset,

    // Maze reset/reload control
    input  logic       map_rst,
    input  logic       reload_done,
    input  logic [1:0] lives,
    input  logic [8:0] pellets,
    input  logic [3:0] inputs,
    output logic [1:0] game_state
);

    localparam logic [1:0]
        GAME_STARTING = 2'd0,
        GAME_PLAYING  = 2'd1,
        GAME_OVER     = 2'd2,
        GAME_WIN      = 2'd3;

    logic [1:0] next_state;

    always_ff @(posedge clk) begin
        if (reset)
            game_state <= GAME_STARTING;
        else
            game_state <= next_state;
    end

    // Next-state logic
    always_comb begin
        next_state = game_state;

        case (game_state)

            // Wait for the maze memory to finish loading.
            GAME_STARTING: begin
                if (reload_done && |inputs)
                    next_state = GAME_PLAYING;
            end

            // Remain here while Pac-Man still has lives.
            GAME_PLAYING: begin
                if (lives == 2'd0)
                    next_state = GAME_OVER;
                else if (pellets == 9'd0)
                    next_state = GAME_WIN;
                else if (map_rst)
                    next_state = GAME_STARTING;
            end

            // Remain in game over until the game is reset.
            GAME_OVER: begin
                if (map_rst || |inputs)
                    next_state = GAME_PLAYING;
            end

            default: begin
                next_state = GAME_STARTING;
            end

        endcase
    end

endmodule

Pacman_FPGA/testbench/game_fsm_tb.sv
`timescale 1ns/1ps

module game_fsm_tb;

    logic       clk;
    logic       reset;
    logic       map_rst;
    logic       reload_done;
    logic [1:0] lives;
    logic [8:0] pellets;
    logic [3:0] inputs;
    logic [1:0] game_state;

    int pass_count;
    int fail_count;

    localparam logic [1:0] GAME_STARTING = 2'd0;
    localparam logic [1:0] GAME_PLAYING  = 2'd1;
    localparam logic [1:0] GAME_OVER     = 2'd2;
    localparam logic [1:0] GAME_WIN      = 2'd3;

    game_fsm dut (
        .clk(clk),
        .reset(reset),
        .map_rst(map_rst),
        .reload_done(reload_done),
        .lives(lives),
        .pellets(pellets),
        .inputs(inputs),
        .game_state(game_state)
    );

    initial clk = 1'b0;
    always #5 clk = ~clk;

    task automatic check(input string name, input logic cond);
        if (cond) begin
            pass_count++;
            $display("PASS: %s", name);
        end else begin
            fail_count++;
            $display("FAIL: %s (game_state=%0d)", name, game_state);
        end
    endtask

    task automatic cycle;
        @(negedge clk);
    endtask

    task automatic sample;
        @(posedge clk);
        #1;
    endtask

    initial begin
        pass_count  = 0;
        fail_count  = 0;
        reset       = 1'b1;
        map_rst     = 1'b0;
        reload_done = 1'b0;
        lives       = 2'd3;
        pellets     = 9'd288;
        inputs      = 4'b0000;

        $dumpfile("waves/game_fsm.vcd");
        $dumpvars(0, game_fsm_tb);

        sample();
        sample();
        cycle();
        reset = 1'b0;
        sample();
        check("reset -> STARTING", game_state === GAME_STARTING);

        cycle();
        reload_done = 1'b1;
        sample();
        check("reload without input stays STARTING", game_state === GAME_STARTING);

        cycle();
        inputs = 4'b0001;
        sample();
        check("reload+input -> PLAYING", game_state === GAME_PLAYING);
        cycle();
        reload_done = 1'b0;
        inputs      = 4'b0000;

        cycle();
        lives = 2'd0;
        sample();
        check("lives==0 -> OVER", game_state === GAME_OVER);

        cycle();
        inputs = 4'b1000;
        sample();
        cycle();
        inputs = 4'b0000;
        check("input from OVER -> STARTING", game_state === GAME_STARTING);

        cycle();
        lives       = 2'd3;
        pellets     = 9'd10;
        reload_done = 1'b1;
        inputs      = 4'b0010;
        sample();
        cycle();
        reload_done = 1'b0;
        inputs      = 4'b0000;
        check("reload again -> PLAYING", game_state === GAME_PLAYING);

        cycle();
        pellets = 9'd0;
        sample();
        check("pellets==0 -> WIN", game_state === GAME_WIN);

        cycle();
        map_rst = 1'b1;
        sample();
        cycle();
        map_rst = 1'b0;
        check("map_rst from WIN -> STARTING", game_state === GAME_STARTING);

        cycle();
        pellets     = 9'd5;
        lives       = 2'd2;
        reload_done = 1'b1;
        inputs      = 4'b0100;
        sample();
        cycle();
        reload_done = 1'b0;
        inputs      = 4'b0000;
        check("playing again", game_state === GAME_PLAYING);

        cycle();
        map_rst = 1'b1;
        sample();
        cycle();
        map_rst = 1'b0;
        check("map_rst from PLAYING -> STARTING", game_state === GAME_STARTING);

        cycle();
        reload_done = 1'b1;
        inputs      = 4'b0001;
        sample();
        cycle();
        reload_done = 1'b0;
        inputs      = 4'b0000;
        cycle();
        reset = 1'b1;
        sample();
        cycle();
        reset = 1'b0;
        sample();
        check("sync reset -> STARTING", game_state === GAME_STARTING);

        $display("\ngame_fsm_tb: %0d PASS, %0d FAIL", pass_count, fail_count);
        $finish;
    end

endmodule

Pacman_FPGA/waves/game_fsm.vcd
$date
	Sat Aug  1 00:16:21 2026
$end
$version
	Icarus Verilog
$end
$timescale
	1ps
$end
$scope module game_fsm_tb $end
$var wire 2 ! game_state [1:0] $end
$var parameter 2 " GAME_OVER $end
$var parameter 2 # GAME_PLAYING $end
$var parameter 2 $ GAME_STARTING $end
$var parameter 2 % GAME_WIN $end
$var reg 1 & clk $end
$var reg 4 ' inputs [3:0] $end
$var reg 2 ( lives [1:0] $end
$var reg 1 ) map_rst $end
$var reg 9 * pellets [8:0] $end
$var reg 1 + reload_done $end
$var reg 1 , reset $end
$var integer 32 - fail_count [31:0] $end
$var integer 32 . pass_count [31:0] $end
$scope module dut $end
$var wire 1 & clk $end
$var wire 4 / inputs [3:0] $end
$var wire 2 0 lives [1:0] $end
$var wire 1 ) map_rst $end
$var wire 9 1 pellets [8:0] $end
$var wire 1 + reload_done $end
$var wire 1 , reset $end
$var parameter 2 2 GAME_OVER $end
$var parameter 2 3 GAME_PLAYING $end
$var parameter 2 4 GAME_STARTING $end
$var parameter 2 5 GAME_WIN $end
$var reg 2 6 game_state [1:0] $end
$var reg 2 7 next_state [1:0] $end
$upscope $end
$scope task check $end
$upscope $end
$scope task cycle $end
$upscope $end
$scope task sample $end
$upscope $end
$upscope $end
$enddefinitions $end
$comment Show the parameter values. $end
$dumpall
b11 5
b0 4
b1 3
b10 2
b11 %
b0 $
b1 #
b10 "
$end
#0
$dumpvars
b0 7
bx 6
b100100000 1
b11 0
b0 /
b0 .
b0 -
1,
0+
b100100000 *
0)
b11 (
b0 '
0&
bx !
$end
#5000
b0 !
b0 6
1&
#10000
0&
#15000
1&
#20000
0,
0&
#25000
1&
#26000
b1 .
#30000
1+
0&
#35000
1&
#36000
b10 .
#40000
b1 7
b1 '
b1 /
0&
#45000
b1 !
b1 6
1&
#46000
b11 .
#50000
b0 '
b0 /
0+
0&
#55000
1&
#60000
b10 7
b0 (
b0 0
0&
#65000
b10 !
b10 6
1&
#66000
b100 .
#70000
b0 7
b1000 '
b1000 /
0&
#75000
b0 !
b0 6
1&
#80000
b101 .
b0 '
b0 /
0&
#85000
1&
#90000
b1 7
b10 '
b10 /
1+
b1010 *
b1010 1
b11 (
b11 0
0&
#95000
b1 !
b1 6
1&
#100000
b110 .
b0 '
b0 /
0+
0&
#105000
1&
#110000
b11 7
b0 *
b0 1
0&
#115000
b11 !
b11 6
1&
#116000
b111 .
#120000
b0 7
1)
0&
#125000
b0 !
b0 6
1&
#130000
b1000 .
0)
0&
#135000
1&
#140000
b1 7
b100 '
b100 /
1+
b10 (
b10 0
b101 *
b101 1
0&
#145000
b1 !
b1 6
1&
#150000
b1001 .
b0 '
b0 /
0+
0&
#155000
1&
#160000
b0 7
1)
0&
#165000
b0 !
b0 6
1&
#170000
b1010 .
0)
0&
#175000
1&
#180000
b1 7
b1 '
b1 /
1+
0&
#185000
b1 !
b1 6
1&
#190000
b0 '
b0 /
0+
0&
#195000
1&
#200000
1,
0&
#205000
b0 7
b0 !
b0 6
1&
#210000
0,
0&
#215000
1&
#216000
b1011 .
