Pacman_FPGA/source/game_fsm.sv
module game_fsm (
    input  logic       clk,
    input  logic       reset,

    // Maze reset/reload control
    input  logic       map_rst,
    input  logic       reload_done,
    input  logic [1:0] lives,
    input  logic [8:0] pellets,
    output logic [1:0] game_state
);

    localparam logic [1:0]
        GAME_STARTING = 2'd0,
        GAME_PLAYING  = 2'd1,
        GAME_OVER     = 2'd2;

    logic [1:0] next_state;

    always_ff @(posedge clk) begin
        if (reset)
            game_state <= GAME_STARTING;
        else
            game_state <= next_state;
    end

    // Next-state logic
    always_comb begin
        next_state = game_state;

        case (game_state)

            // Wait for the maze memory to finish loading.
            GAME_STARTING: begin
                if (reload_done)
                    next_state = GAME_PLAYING;
            end

            // Remain here while Pac-Man still has lives.
            GAME_PLAYING: begin
                if (lives == 2'd0 || pellets == 9'd0)
                    next_state = GAME_OVER;
                else if (map_rst)
                    next_state = GAME_STARTING;
            end

            // Remain in game over until the game is reset.
            GAME_OVER: begin
                if (map_rst)
                    next_state = GAME_STARTING;
            end

            default: begin
                next_state = GAME_STARTING;
            end

        endcase
    end

endmodule

Pacman_FPGA/testbench/game_fsm_tb.sv
`timescale 1ns/1ps

module game_fsm_tb;

    logic       clk;
    logic       reset;
    logic       map_rst;
    logic       reload_done;
    logic [1:0] lives;
    logic [8:0] pellets;
    logic [1:0] game_state;

    int pass_count;
    int fail_count;

    localparam logic [1:0] GAME_STARTING = 2'd0;
    localparam logic [1:0] GAME_PLAYING  = 2'd1;
    localparam logic [1:0] GAME_OVER     = 2'd2;

    game_fsm dut (
        .clk(clk),
        .reset(reset),
        .map_rst(map_rst),
        .reload_done(reload_done),
        .lives(lives),
        .pellets(pellets),
        .game_state(game_state)
    );

    initial clk = 1'b0;
    always #5 clk = ~clk;

    task automatic check(input string name, input logic cond);
        if (cond) begin
            pass_count++;
            $display("PASS: %s", name);
        end else begin
            fail_count++;
            $display("FAIL: %s (game_state=%0d)", name, game_state);
        end
    endtask

    // Drive on negedge, sample after posedge
    task automatic cycle;
        @(negedge clk);
    endtask

    task automatic sample;
        @(posedge clk);
        #1;
    endtask

    initial begin
        pass_count  = 0;
        fail_count  = 0;
        reset       = 1'b1;
        map_rst     = 1'b0;
        reload_done = 1'b0;
        lives       = 2'd3;
        pellets     = 9'd288;

        $dumpfile("waves/game_fsm.vcd");
        $dumpvars(0, game_fsm_tb);

        sample();
        sample();
        cycle();
        reset = 1'b0;
        sample();
        check("reset -> STARTING", game_state === GAME_STARTING);

        sample();
        sample();
        check("wait without reload", game_state === GAME_STARTING);

        cycle();
        reload_done = 1'b1;
        sample();
        check("reload_done -> PLAYING", game_state === GAME_PLAYING);
        cycle();
        reload_done = 1'b0;

        cycle();
        lives = 2'd0;
        sample();
        check("lives==0 -> OVER", game_state === GAME_OVER);

        cycle();
        map_rst = 1'b1;
        sample();
        cycle();
        map_rst = 1'b0;
        check("map_rst from OVER -> STARTING", game_state === GAME_STARTING);

        cycle();
        lives       = 2'd3;
        pellets     = 9'd10;
        reload_done = 1'b1;
        sample();
        cycle();
        reload_done = 1'b0;
        check("reload again -> PLAYING", game_state === GAME_PLAYING);

        cycle();
        pellets = 9'd0;
        sample();
        check("pellets==0 -> OVER", game_state === GAME_OVER);

        cycle();
        map_rst = 1'b1;
        sample();
        cycle();
        map_rst = 1'b0;
        check("map_rst from OVER path -> STARTING", game_state === GAME_STARTING);

        cycle();
        pellets     = 9'd5;
        lives       = 2'd2;
        reload_done = 1'b1;
        sample();
        cycle();
        reload_done = 1'b0;
        check("playing again", game_state === GAME_PLAYING);

        cycle();
        map_rst = 1'b1;
        sample();
        cycle();
        map_rst = 1'b0;
        check("map_rst from PLAYING -> STARTING", game_state === GAME_STARTING);

        cycle();
        reload_done = 1'b1;
        sample();
        cycle();
        reload_done = 1'b0;
        cycle();
        reset = 1'b1;
        sample();
        cycle();
        reset = 1'b0;
        sample();
        check("sync reset -> STARTING", game_state === GAME_STARTING);

        $display("\ngame_fsm_tb: %0d PASS, %0d FAIL", pass_count, fail_count);
        $finish;
    end

endmodule

Pacman_FPGA/waves/game_fsm.vcd
$date
	Fri Jul 24 16:24:14 2026
$end
$version
	Icarus Verilog
$end
$timescale
	1ps
$end
$scope module game_fsm_tb $end
$var wire 2 ! game_state [1:0] $end
$var parameter 2 " GAME_OVER $end
$var parameter 2 # GAME_PLAYING $end
$var parameter 2 $ GAME_STARTING $end
$var reg 1 % clk $end
$var reg 2 & lives [1:0] $end
$var reg 1 ' map_rst $end
$var reg 9 ( pellets [8:0] $end
$var reg 1 ) reload_done $end
$var reg 1 * reset $end
$var integer 32 + fail_count [31:0] $end
$var integer 32 , pass_count [31:0] $end
$scope module dut $end
$var wire 1 % clk $end
$var wire 2 - lives [1:0] $end
$var wire 1 ' map_rst $end
$var wire 9 . pellets [8:0] $end
$var wire 1 ) reload_done $end
$var wire 1 * reset $end
$var parameter 2 / GAME_OVER $end
$var parameter 2 0 GAME_PLAYING $end
$var parameter 2 1 GAME_STARTING $end
$var reg 2 2 game_state [1:0] $end
$var reg 2 3 next_state [1:0] $end
$upscope $end
$scope task check $end
$upscope $end
$scope task cycle $end
$upscope $end
$scope task sample $end
$upscope $end
$upscope $end
$enddefinitions $end
$comment Show the parameter values. $end
$dumpall
b0 1
b1 0
b10 /
b0 $
b1 #
b10 "
$end
#0
$dumpvars
b0 3
bx 2
b100100000 .
b11 -
b0 ,
b0 +
1*
0)
b100100000 (
0'
b11 &
0%
bx !
$end
#5000
b0 !
b0 2
1%
#10000
0%
#15000
1%
#20000
0*
0%
#25000
1%
#26000
b1 ,
#30000
0%
#35000
1%
#40000
0%
#45000
1%
#46000
b10 ,
#50000
b1 3
1)
0%
#55000
b1 !
b1 2
1%
#56000
b11 ,
#60000
0)
0%
#65000
1%
#70000
b10 3
b0 &
b0 -
0%
#75000
b10 !
b10 2
1%
#76000
b100 ,
#80000
b0 3
1'
0%
#85000
b0 !
b0 2
1%
#90000
b101 ,
0'
0%
#95000
1%
#100000
b1 3
1)
b1010 (
b1010 .
b11 &
b11 -
0%
#105000
b1 !
b1 2
1%
#110000
b110 ,
0)
0%
#115000
1%
#120000
b10 3
b0 (
b0 .
0%
#125000
b10 !
b10 2
1%
#126000
b111 ,
#130000
b0 3
1'
0%
#135000
b0 !
b0 2
1%
#140000
b1000 ,
0'
0%
#145000
1%
#150000
b1 3
1)
b10 &
b10 -
b101 (
b101 .
0%
#155000
b1 !
b1 2
1%
#160000
b1001 ,
0)
0%
#165000
1%
#170000
b0 3
1'
0%
#175000
b0 !
b0 2
1%
#180000
b1010 ,
0'
0%
#185000
1%
#190000
b1 3
1)
0%
#195000
b1 !
b1 2
1%
#200000
0)
0%
#205000
1%
#210000
1*
0%
#215000
b0 3
b0 !
b0 2
1%
#220000
0*
0%
#225000
1%
#226000
b1011 ,
