ghost_fsm.sv
`timescale 1ns/1ps

module ghost_fsm (
    input  logic       clk,
    input  logic       reset,

    input  logic [1:0] game_state,
    input  logic       power_pellet_active,
    input  logic       ghost_eaten,
    input  logic       global_ghost_mode,

    output logic [1:0] ghost_state,
    output logic       ghost_can_move,
    output logic       dangerous_to_pacman,
    output logic       vulnerable_to_pacman,
    output logic       frightened_start
);

    // Game FSM encodings
    localparam logic [1:0] GAME_STARTING = 2'd0;
    localparam logic [1:0] GAME_PLAYING  = 2'd1;
    localparam logic [1:0] GAME_OVER     = 2'd2;

    // Ghost state encodings
    localparam logic [1:0] G_CAGED      = 2'd0;
    localparam logic [1:0] G_SCATTER    = 2'd1;
    localparam logic [1:0] G_CHASE      = 2'd2;
    localparam logic [1:0] G_FRIGHTENED = 2'd3;

    // Global ghost mode
    localparam logic GLOBAL_SCATTER = 1'b0;
    localparam logic GLOBAL_CHASE   = 1'b1;

    logic [1:0] state;
    logic [1:0] next_state;

    assign ghost_state = state;

    // State register; frightened pulse
    always_ff @(posedge clk or posedge reset) begin
        if (reset)
            state <= G_CAGED;
            frightened_start <= 1'b0;
        else
            state <= next_state;
            frightened_start <= (state != G_FRIGHTENED) &&
                                (next_state == G_FRIGHTENED);
    end

    // Next-state logic
    always_comb begin
        next_state = state;

        if (game_state != GAME_PLAYING) begin
            next_state = G_CAGED;
        end else begin
            case (state)

                G_CAGED: begin
                    if (global_ghost_mode == GLOBAL_SCATTER)
                        next_state = G_SCATTER;
                    else
                        next_state = G_CHASE;
                end

                G_SCATTER: begin
                    if (power_pellet_active)
                        next_state = G_FRIGHTENED;
                    else if (global_ghost_mode == GLOBAL_CHASE)
                        next_state = G_CHASE;
                end

                G_CHASE: begin
                    if (power_pellet_active)
                        next_state = G_FRIGHTENED;
                    else if (global_ghost_mode == GLOBAL_SCATTER)
                        next_state = G_SCATTER;
                end

                G_FRIGHTENED: begin
                    if (ghost_eaten)
                        next_state = G_CAGED;
                    else if (!power_pellet_active) begin
                        if (global_ghost_mode == GLOBAL_SCATTER)
                            next_state = G_SCATTER;
                        else
                            next_state = G_CHASE;
                    end
                end

                default: begin
                    next_state = G_CAGED;
                end

            endcase
        end
    end

    // Decoded outputs
    always_comb begin
        ghost_can_move       = (state != G_CAGED);
        dangerous_to_pacman  = (state == G_SCATTER) || (state == G_CHASE);
        vulnerable_to_pacman = (state == G_FRIGHTENED);
    end

endmodule

Pacman_FPGA/testbench/ghost_fsm_tb.sv
`timescale 1ns/1ps

module ghost_fsm_tb;

    logic       clk;
    logic       reset;
    logic [1:0] game_state;
    logic       power_pellet_active;
    logic       ghost_eaten;
    logic       global_ghost_mode;

    logic [1:0] ghost_state;
    logic       ghost_can_move;
    logic       dangerous_to_pacman;
    logic       vulnerable_to_pacman;
    logic       frightened_start;

    int pass_count;
    int fail_count;

    localparam logic [1:0] GAME_STARTING = 2'd0;
    localparam logic [1:0] GAME_PLAYING  = 2'd1;
    localparam logic [1:0] GAME_OVER     = 2'd2;

    localparam logic [1:0] G_CAGED      = 2'd0;
    localparam logic [1:0] G_SCATTER    = 2'd1;
    localparam logic [1:0] G_CHASE      = 2'd2;
    localparam logic [1:0] G_FRIGHTENED = 2'd3;

    ghost_fsm dut (
        .clk(clk),
        .reset(reset),
        .game_state(game_state),
        .power_pellet_active(power_pellet_active),
        .ghost_eaten(ghost_eaten),
        .global_ghost_mode(global_ghost_mode),
        .ghost_state(ghost_state),
        .ghost_can_move(ghost_can_move),
        .dangerous_to_pacman(dangerous_to_pacman),
        .vulnerable_to_pacman(vulnerable_to_pacman),
        .frightened_start(frightened_start)
    );

    initial clk = 1'b0;
    always #5 clk = ~clk;

    task automatic check(input string name, input logic cond);
        if (cond) begin
            pass_count++;
            $display("PASS: %s", name);
        end else begin
            fail_count++;
            $display("FAIL: %s (ghost_state=%0d fs=%b)", name, ghost_state, frightened_start);
        end
    endtask

    task automatic cycle;
        @(negedge clk);
    endtask

    task automatic sample;
        @(posedge clk);
        #1;
    endtask

    initial begin
        pass_count           = 0;
        fail_count           = 0;
        reset                = 1'b1;
        game_state           = GAME_STARTING;
        power_pellet_active  = 1'b0;
        ghost_eaten          = 1'b0;
        global_ghost_mode    = 1'b0;

        $dumpfile("waves/ghost_fsm.vcd");
        $dumpvars(0, ghost_fsm_tb);

        sample();
        sample();
        cycle();
        reset = 1'b0;
        sample();
        check("reset -> CAGED", ghost_state === G_CAGED);
        check("caged cannot move", ghost_can_move === 1'b0);
        check("caged not dangerous", dangerous_to_pacman === 1'b0);

        cycle();
        game_state        = GAME_OVER;
        global_ghost_mode = 1'b1;
        sample();
        sample();
        check("non-playing stays CAGED", ghost_state === G_CAGED);

        cycle();
        game_state        = GAME_PLAYING;
        global_ghost_mode = 1'b0;
        power_pellet_active = 1'b0;
        sample();
        check("caged -> SCATTER", ghost_state === G_SCATTER);
        check("scatter can move", ghost_can_move === 1'b1);
        check("scatter dangerous", dangerous_to_pacman === 1'b1);
        check("scatter not vulnerable", vulnerable_to_pacman === 1'b0);

        cycle();
        global_ghost_mode = 1'b1;
        sample();
        check("scatter -> CHASE", ghost_state === G_CHASE);
        check("chase dangerous", dangerous_to_pacman === 1'b1);

        cycle();
        power_pellet_active = 1'b1;
        sample();
        check("chase -> FRIGHTENED", ghost_state === G_FRIGHTENED);
        check("frightened_start pulse", frightened_start === 1'b1);
        check("frightened can move", ghost_can_move === 1'b1);
        check("frightened vulnerable", vulnerable_to_pacman === 1'b1);
        check("frightened not dangerous", dangerous_to_pacman === 1'b0);
        sample();
        check("frightened_start clears", frightened_start === 1'b0);

        sample();
        sample();
        sample();
        check("stay FRIGHTENED", ghost_state === G_FRIGHTENED);

        cycle();
        power_pellet_active = 1'b0;
        sample();
        check("frightened -> CHASE", ghost_state === G_CHASE);

        cycle();
        power_pellet_active = 1'b1;
        sample();
        check("again FRIGHTENED", ghost_state === G_FRIGHTENED);
        cycle();
        ghost_eaten = 1'b1;
        sample();
        cycle();
        ghost_eaten = 1'b0;
        check("eaten -> CAGED", ghost_state === G_CAGED);

        sample();
        sample();
        check("caged while pellet active", ghost_state === G_CAGED);

        cycle();
        power_pellet_active = 1'b0;
        global_ghost_mode   = 1'b0;
        sample();
        check("leave cage to SCATTER", ghost_state === G_SCATTER);

        cycle();
        power_pellet_active = 1'b1;
        sample();
        cycle();
        power_pellet_active = 1'b0;
        sample();
        check("frightened -> SCATTER", ghost_state === G_SCATTER);

        cycle();
        game_state = GAME_STARTING;
        sample();
        check("starting forces CAGED", ghost_state === G_CAGED);

        $display("\nghost_fsm_tb: %0d PASS, %0d FAIL", pass_count, fail_count);
        if (fail_count != 0) $fatal(1);
        $finish;
    end

endmodule

Pacman_FPGA/waves/ghost_fsm.vcd
$date
	Sat Aug  1 22:09:53 2026
$end
$version
	Icarus Verilog
$end
$timescale
	1ps
$end
$scope module ghost_fsm_tb $end
$var wire 1 ! vulnerable_to_pacman $end
$var wire 2 " ghost_state [1:0] $end
$var wire 1 # ghost_can_move $end
$var wire 1 $ frightened_start $end
$var wire 1 % dangerous_to_pacman $end
$var parameter 2 & GAME_OVER $end
$var parameter 2 ' GAME_PLAYING $end
$var parameter 2 ( GAME_STARTING $end
$var parameter 2 ) G_CAGED $end
$var parameter 2 * G_CHASE $end
$var parameter 2 + G_FRIGHTENED $end
$var parameter 2 , G_SCATTER $end
$var reg 1 - clk $end
$var reg 2 . game_state [1:0] $end
$var reg 1 / ghost_eaten $end
$var reg 1 0 global_ghost_mode $end
$var reg 1 1 power_pellet_active $end
$var reg 1 2 reset $end
$var integer 32 3 fail_count [31:0] $end
$var integer 32 4 pass_count [31:0] $end
$scope module dut $end
$var wire 1 - clk $end
$var wire 2 5 game_state [1:0] $end
$var wire 1 / ghost_eaten $end
$var wire 2 6 ghost_state [1:0] $end
$var wire 1 0 global_ghost_mode $end
$var wire 1 1 power_pellet_active $end
$var wire 1 2 reset $end
$var parameter 2 7 GAME_OVER $end
$var parameter 2 8 GAME_PLAYING $end
$var parameter 2 9 GAME_STARTING $end
$var parameter 1 : GLOBAL_CHASE $end
$var parameter 1 ; GLOBAL_SCATTER $end
$var parameter 2 < G_CAGED $end
$var parameter 2 = G_CHASE $end
$var parameter 2 > G_FRIGHTENED $end
$var parameter 2 ? G_SCATTER $end
$var reg 1 % dangerous_to_pacman $end
$var reg 1 $ frightened_start $end
$var reg 1 # ghost_can_move $end
$var reg 2 @ next_state [1:0] $end
$var reg 2 A state [1:0] $end
$var reg 1 ! vulnerable_to_pacman $end
$upscope $end
$scope task check $end
$upscope $end
$scope task cycle $end
$upscope $end
$scope task sample $end
$upscope $end
$upscope $end
$enddefinitions $end
$comment Show the parameter values. $end
$dumpall
b1 ?
b11 >
b10 =
b0 <
0;
1:
b0 9
b1 8
b10 7
b1 ,
b11 +
b10 *
b0 )
b0 (
b1 '
b10 &
$end
#0
$dumpvars
b0 A
b0 @
b0 6
b0 5
b0 4
b0 3
12
01
00
0/
b0 .
0-
0%
0$
0#
b0 "
0!
$end
#5000
1-
#10000
0-
#15000
1-
#20000
02
0-
#25000
1-
#26000
b11 4
#30000
10
b10 .
b10 5
0-
#35000
1-
#40000
0-
#45000
1-
#46000
b100 4
#50000
b1 @
00
b1 .
b1 5
0-
#55000
1%
1#
b1 "
b1 6
b1 A
1-
#56000
b1000 4
#60000
b10 @
10
0-
#65000
b10 "
b10 6
b10 A
1-
#66000
b1010 4
#70000
1!
0%
b11 @
11
0-
#75000
1$
b11 "
b11 6
b11 A
1-
#76000
b1111 4
#80000
0-
#85000
0$
1-
#86000
b10000 4
#90000
0-
#95000
1-
#100000
0-
#105000
1-
#110000
0-
#115000
1-
#116000
b10001 4
#120000
b10 @
01
0-
#125000
0!
1%
b10 "
b10 6
b10 A
1-
#126000
b10010 4
#130000
1!
0%
b11 @
11
0-
#135000
1$
b11 "
b11 6
b11 A
1-
#136000
b10011 4
#140000
b0 @
1/
0-
#145000
0!
0#
0$
b0 "
b0 6
b0 A
1-
#150000
b10100 4
0/
0-
#155000
1-
#160000
0-
#165000
1-
#166000
b10101 4
#170000
b1 @
00
01
0-
#175000
1%
1#
b1 "
b1 6
b1 A
1-
#176000
b10110 4
#180000
1!
0%
b11 @
11
0-
#185000
1$
b11 "
b11 6
b11 A
1-
#190000
b1 @
01
0-
#195000
0!
1%
0$
b1 "
b1 6
b1 A
1-
#196000
b10111 4
#200000
b0 @
b0 .
b0 5
0-
#205000
0%
0#
b0 "
b0 6
b0 A
1-
#206000
b11000 4
