Pacman_FPGA/source/ghost_movement.sv
module ghost_movement (
    input  logic           ghost_can_move,

    input  logic [4:0] ghost_x,
    input  logic [4:0] ghost_y,
    input  logic [1:0] ghost_dir,

    input  logic [4:0] target_x,
    input  logic [4:0] target_y,

    input  logic       can_up,
    input  logic       can_down,
    input  logic       can_left,
    input  logic       can_right,

    input  logic       do_reverse,

    output logic [4:0] next_x,
    output logic [4:0] next_y,
    output logic [1:0] next_dir
);

    localparam logic [1:0] DIR_UP    = 2'd0;
    localparam logic [1:0] DIR_DOWN  = 2'd1;
    localparam logic [1:0] DIR_LEFT  = 2'd2;
    localparam logic [1:0] DIR_RIGHT = 2'd3;

    logic [1:0] reverse_dir;

    function automatic logic legal(
        input logic [1:0] direction
    );
        begin
            case (direction)
                DIR_UP:    legal = can_up;
                DIR_DOWN:  legal = can_down;
                DIR_LEFT:  legal = can_left;
                DIR_RIGHT: legal = can_right;
                default:   legal = 1'b0;
            endcase
        end
    endfunction

    assign reverse_dir = ghost_dir ^ 2'b01;

    always_comb begin
        next_dir = ghost_dir;

        if (ghost_can_move) begin
            // Reverse once when frightened mode begins.
            if (do_reverse && legal(reverse_dir)) begin
                next_dir = reverse_dir;
            end

            // Move toward the target without reversing.
            else if ((target_x > ghost_x) && can_right && (reverse_dir != DIR_RIGHT)) begin
                next_dir = DIR_RIGHT;
            end

            else if ((target_x < ghost_x) && can_left && (reverse_dir != DIR_LEFT)) begin
                next_dir = DIR_LEFT;
            end

            else if ((target_y > ghost_y) && can_down && (reverse_dir != DIR_DOWN)) begin
                next_dir = DIR_DOWN;
            end

            else if ((target_y < ghost_y) && can_up && (reverse_dir != DIR_UP)) begin
                next_dir = DIR_UP;
            end

            // Continue straight when possible.
            else if (legal(ghost_dir)) begin
                next_dir = ghost_dir;
            end

            // Select another legal non-reverse direction.
            else if (can_up && (reverse_dir != DIR_UP)) begin
                next_dir = DIR_UP;
            end

            else if (can_left && (reverse_dir != DIR_LEFT)) begin
                next_dir = DIR_LEFT;
            end

            else if (can_down && (reverse_dir != DIR_DOWN)) begin
                next_dir = DIR_DOWN;
            end

            else if (can_right && (reverse_dir != DIR_RIGHT)) begin
                next_dir = DIR_RIGHT;
            end

            // Reverse only when no other direction is available.
            else if (legal(reverse_dir)) begin
                next_dir = reverse_dir;
            end
        end

        next_x = ghost_x;
        next_y = ghost_y;

        // Move only when the selected direction is confirmed legal.
        if (ghost_can_move && legal(next_dir)) begin
            case (next_dir)
                DIR_UP:
                    next_y = ghost_y - 1'b1;

                DIR_DOWN:
                    next_y = ghost_y + 1'b1;

                DIR_LEFT:
                    next_x = ghost_x - 1'b1;

                DIR_RIGHT:
                    next_x = ghost_x + 1'b1;

                default: begin
                    next_x = ghost_x;
                    next_y = ghost_y;
                end
            endcase
        end
    end

endmodule

Pacman_FPGA/testbench/ghost_movement_tb.sv
`timescale 1ns/1ps

module ghost_movement_tb;

    logic       ghost_can_move;
    logic [4:0] ghost_x;
    logic [4:0] ghost_y;
    logic [1:0] ghost_dir;
    logic [4:0] target_x;
    logic [4:0] target_y;
    logic       can_up;
    logic       can_down;
    logic       can_left;
    logic       can_right;
    logic       do_reverse;
    logic [4:0] next_x;
    logic [4:0] next_y;
    logic [1:0] next_dir;

    int pass_count;
    int fail_count;

    localparam logic [1:0] DIR_UP    = 2'd0;
    localparam logic [1:0] DIR_LEFT  = 2'd1;
    localparam logic [1:0] DIR_DOWN  = 2'd2;
    localparam logic [1:0] DIR_RIGHT = 2'd3;

    ghost_movement dut (
        .ghost_can_move(ghost_can_move),
        .ghost_x(ghost_x),
        .ghost_y(ghost_y),
        .ghost_dir(ghost_dir),
        .target_x(target_x),
        .target_y(target_y),
        .can_up(can_up),
        .can_down(can_down),
        .can_left(can_left),
        .can_right(can_right),
        .do_reverse(do_reverse),
        .next_x(next_x),
        .next_y(next_y),
        .next_dir(next_dir)
    );

    task automatic check(input string name, input logic cond);
        if (cond) begin
            pass_count++;
            $display("PASS: %s", name);
        end else begin
            fail_count++;
            $display("FAIL: %s (dir=%0d x=%0d y=%0d)", name, next_dir, next_x, next_y);
        end
    endtask

    task automatic set_open_all;
        can_up    = 1'b1;
        can_down  = 1'b1;
        can_left  = 1'b1;
        can_right = 1'b1;
    endtask

    initial begin
        pass_count     = 0;
        fail_count     = 0;
        ghost_can_move = 1'b0;
        ghost_x        = 5'd10;
        ghost_y        = 5'd10;
        ghost_dir      = DIR_RIGHT;
        target_x       = 5'd15;
        target_y       = 5'd10;
        do_reverse     = 1'b0;
        set_open_all();

        $dumpfile("waves/ghost_movement.vcd");
        $dumpvars(0, ghost_movement_tb);

        #1;
        check("cannot move holds pose",
              (next_dir === DIR_RIGHT) && (next_x === 5'd10) && (next_y === 5'd10));

        // Prefer right toward target
        ghost_can_move = 1'b1;
        #1;
        check("move right toward target",
              (next_dir === DIR_RIGHT) && (next_x === 5'd11) && (next_y === 5'd10));

        // Prefer left
        target_x  = 5'd5;
        ghost_dir = DIR_LEFT;
        #1;
        check("move left toward target",
              (next_dir === DIR_LEFT) && (next_x === 5'd9) && (next_y === 5'd10));

        // Prefer down (x equal)
        target_x  = 5'd10;
        target_y  = 5'd15;
        ghost_dir = DIR_DOWN;
        #1;
        check("move down toward target",
              (next_dir === DIR_DOWN) && (next_x === 5'd10) && (next_y === 5'd11));

        // Prefer up
        target_y  = 5'd5;
        ghost_dir = DIR_UP;
        #1;
        check("move up toward target",
              (next_dir === DIR_UP) && (next_x === 5'd10) && (next_y === 5'd9));

        // do_reverse takes reverse when legal
        ghost_dir  = DIR_RIGHT;
        target_x   = 5'd20;
        target_y   = 5'd10;
        do_reverse = 1'b1;
        #1;
        check("do_reverse chooses left",
              (next_dir === DIR_LEFT) && (next_x === 5'd9) && (next_y === 5'd10));
        do_reverse = 1'b0;

        // Continue straight when target axes blocked / reverse-only
        ghost_x   = 5'd10;
        ghost_y   = 5'd10;
        ghost_dir = DIR_RIGHT;
        target_x  = 5'd10;
        target_y  = 5'd10;
        can_up    = 1'b0;
        can_down  = 1'b0;
        can_left  = 1'b0;
        can_right = 1'b1;
        #1;
        check("continue straight",
              (next_dir === DIR_RIGHT) && (next_x === 5'd11) && (next_y === 5'd10));

        // Alternate non-reverse when forward blocked
        can_right = 1'b0;
        can_up    = 1'b1;
        can_left  = 1'b0;
        can_down  = 1'b0;
        ghost_dir = DIR_RIGHT;
        #1;
        check("pick up when forward blocked",
              (next_dir === DIR_UP) && (next_x === 5'd10) && (next_y === 5'd9));

        // Dead-end forces reverse
        can_up    = 1'b0;
        can_down  = 1'b0;
        can_left  = 1'b1;
        can_right = 1'b0;
        ghost_dir = DIR_RIGHT;
        #1;
        check("dead-end reverse",
              (next_dir === DIR_LEFT) && (next_x === 5'd9) && (next_y === 5'd10));

        // Illegal chosen dir does not update position
        set_open_all();
        can_right = 1'b0;
        can_left  = 1'b0;
        can_up    = 1'b0;
        can_down  = 1'b0;
        ghost_dir = DIR_RIGHT;
        target_x  = 5'd20;
        #1;
        check("no legal move holds position",
              (next_x === 5'd10) && (next_y === 5'd10));

        $display("\nghost_movement_tb: %0d PASS, %0d FAIL", pass_count, fail_count);
        if (fail_count != 0) $fatal(1);
        $finish;
    end

endmodule

Pacman_FPGA/waves/ghost_movement.vcd
$date
	Sat Aug  1 22:09:53 2026
$end
$version
	Icarus Verilog
$end
$timescale
	1ps
$end
$scope module ghost_movement_tb $end
$var wire 5 ! next_y [4:0] $end
$var wire 5 " next_x [4:0] $end
$var wire 2 # next_dir [1:0] $end
$var parameter 2 $ DIR_DOWN $end
$var parameter 2 % DIR_LEFT $end
$var parameter 2 & DIR_RIGHT $end
$var parameter 2 ' DIR_UP $end
$var reg 1 ( can_down $end
$var reg 1 ) can_left $end
$var reg 1 * can_right $end
$var reg 1 + can_up $end
$var reg 1 , do_reverse $end
$var reg 1 - ghost_can_move $end
$var reg 2 . ghost_dir [1:0] $end
$var reg 5 / ghost_x [4:0] $end
$var reg 5 0 ghost_y [4:0] $end
$var reg 5 1 target_x [4:0] $end
$var reg 5 2 target_y [4:0] $end
$var integer 32 3 fail_count [31:0] $end
$var integer 32 4 pass_count [31:0] $end
$scope module dut $end
$var wire 1 ( can_down $end
$var wire 1 ) can_left $end
$var wire 1 * can_right $end
$var wire 1 + can_up $end
$var wire 1 , do_reverse $end
$var wire 1 - ghost_can_move $end
$var wire 2 5 ghost_dir [1:0] $end
$var wire 5 6 ghost_x [4:0] $end
$var wire 5 7 ghost_y [4:0] $end
$var wire 2 8 reverse_dir [1:0] $end
$var wire 5 9 target_x [4:0] $end
$var wire 5 : target_y [4:0] $end
$var parameter 2 ; DIR_DOWN $end
$var parameter 2 < DIR_LEFT $end
$var parameter 2 = DIR_RIGHT $end
$var parameter 2 > DIR_UP $end
$var reg 2 ? next_dir [1:0] $end
$var reg 5 @ next_x [4:0] $end
$var reg 5 A next_y [4:0] $end
$scope function legal $end
$upscope $end
$upscope $end
$scope task check $end
$upscope $end
$scope task set_open_all $end
$upscope $end
$upscope $end
$enddefinitions $end
$comment Show the parameter values. $end
$dumpall
b0 >
b11 =
b1 <
b10 ;
b0 '
b11 &
b1 %
b10 $
$end
#0
$dumpvars
b1010 A
b1010 @
b11 ?
b1010 :
b1111 9
b1 8
b1010 7
b1010 6
b11 5
b0 4
b0 3
b1010 2
b1111 1
b1010 0
b1010 /
b11 .
0-
0,
1+
1*
1)
1(
b11 #
b1010 "
b1010 !
$end
#1000
b1011 "
b1011 @
1-
b1 4
#2000
b11 8
b1001 "
b1001 @
b1 #
b1 ?
b1 .
b1 5
b101 1
b101 9
b10 4
#3000
b0 8
b1011 !
b1011 A
b1010 "
b1010 @
b10 #
b10 ?
b10 .
b10 5
b1111 2
b1111 :
b1010 1
b1010 9
b11 4
#4000
b10 8
b1001 !
b1001 A
b0 #
b0 ?
b0 .
b0 5
b101 2
b101 :
b100 4
#5000
b1001 "
b1001 @
b1 8
b1010 !
b1010 A
b1 #
b1 ?
1,
b1010 2
b1010 :
b10100 1
b10100 9
b11 .
b11 5
b101 4
#6000
b1011 "
b1011 @
b11 #
b11 ?
0)
0(
0+
b1010 1
b1010 9
0,
b110 4
#7000
b1001 !
b1001 A
b1010 "
b1010 @
b0 #
b0 ?
1+
0*
b111 4
#8000
b1001 "
b1001 @
b1010 !
b1010 A
b1 #
b1 ?
1)
0+
b1000 4
#9000
b1010 "
b1010 @
b11 #
b11 ?
b10100 1
b10100 9
0)
0*
0(
0+
b1001 4
#10000
b1010 4
