Pacman_FPGA/source/initial_maze_rom.sv
`timescale 1ns/1ps

module initial_maze_rom (
    // Port A: reload or Pac-Man movement
    input  logic [4:0] x_a,
    input  logic [4:0] y_a,
    output logic [1:0] tile_a,
    output logic       can_move_a,

    // Port B: ghost movement
    input  logic [4:0] x_b,
    input  logic [4:0] y_b,
    output logic [1:0] tile_b,
    output logic       can_move_b
);

    localparam logic [1:0] PATH_TILE  = 2'b00;
    localparam logic [1:0] WALL_TILE  = 2'b01;
    localparam logic [1:0] PELLET     = 2'b10;
    localparam logic [1:0] POWER_TILE = 2'b11;

    logic [55:0] maze [0:30];

    initial begin
        maze[0]  = {28{2'b01}};
        maze[1]  = 56'b01_11_10_10_10_10_10_10_10_10_10_10_10_01_01_10_10_10_10_10_10_10_10_10_10_10_11_01;
        maze[2]  = 56'b01_10_01_01_01_01_10_01_01_01_01_01_10_01_01_10_01_01_01_01_01_10_01_01_01_01_10_01;
        maze[3]  = 56'b01_10_01_01_01_01_10_01_01_01_01_01_10_01_01_10_01_01_01_01_01_10_01_01_01_01_10_01;
        maze[4]  = 56'b01_10_01_01_01_01_10_01_01_01_01_01_10_01_01_10_01_01_01_01_01_10_01_01_01_01_10_01;
        maze[5]  = 56'b01_10_10_10_10_10_10_10_10_10_10_10_10_10_10_10_10_10_10_10_10_10_10_10_10_10_10_01;
        maze[6]  = 56'b01_10_01_01_01_01_10_01_01_10_01_01_01_01_01_01_01_01_10_01_01_10_01_01_01_01_10_01;
        maze[7]  = 56'b01_10_01_01_01_01_10_01_01_10_01_01_01_01_01_01_01_01_10_01_01_10_01_01_01_01_10_01;
        maze[8]  = 56'b01_10_10_10_10_10_10_01_01_10_10_10_10_01_01_10_10_10_10_01_01_10_10_10_10_10_10_01;
        maze[9]  = 56'b01_01_01_01_01_01_10_01_01_01_01_01_10_01_01_10_01_01_01_01_01_10_01_01_01_01_01_01;
        maze[10] = 56'b01_01_01_01_01_01_10_01_01_01_01_01_10_01_01_10_01_01_01_01_01_10_01_01_01_01_01_01;
        maze[11] = 56'b01_01_01_01_01_01_10_01_01_10_10_10_10_10_10_10_10_10_10_01_01_10_01_01_01_01_01_01;
        maze[12] = 56'b01_01_01_01_01_01_10_01_01_10_01_01_01_00_00_01_01_01_10_01_01_10_01_01_01_01_01_01;
        maze[13] = 56'b01_01_01_01_01_01_10_01_01_10_01_00_00_00_00_00_00_01_10_01_01_10_01_01_01_01_01_01;
        maze[14] = 56'b00_00_00_00_00_00_10_10_10_10_01_00_00_00_00_00_00_01_10_10_10_10_00_00_00_00_00_00;
        maze[15] = 56'b01_01_01_01_01_01_10_01_01_10_01_00_00_00_00_00_00_01_10_01_01_10_01_01_01_01_01_01;
        maze[16] = 56'b01_01_01_01_01_01_10_01_01_10_01_01_01_01_01_01_01_01_10_01_01_10_01_01_01_01_01_01;
        maze[17] = 56'b01_01_01_01_01_01_10_01_01_10_10_10_10_10_10_10_10_10_10_01_01_10_01_01_01_01_01_01;
        maze[18] = 56'b01_01_01_01_01_01_10_01_01_10_01_01_01_01_01_01_01_01_10_01_01_10_01_01_01_01_01_01;
        maze[19] = 56'b01_01_01_01_01_01_10_01_01_10_01_01_01_01_01_01_01_01_10_01_01_10_01_01_01_01_01_01;
        maze[20] = 56'b01_10_10_10_10_10_10_10_10_10_10_10_10_01_01_10_10_10_10_10_10_10_10_10_10_10_10_01;
        maze[21] = 56'b01_10_01_01_01_01_10_01_01_01_01_01_10_01_01_10_01_01_01_01_01_10_01_01_01_01_10_01;
        maze[22] = 56'b01_10_01_01_01_01_10_01_01_01_01_01_10_01_01_10_01_01_01_01_01_10_01_01_01_01_10_01;
        maze[23] = 56'b01_10_10_10_01_01_10_10_10_10_10_10_10_10_10_10_10_10_10_10_10_10_01_01_10_10_10_01;
        maze[24] = 56'b01_01_01_10_01_01_10_01_01_10_01_01_01_01_01_01_01_01_10_01_01_10_01_01_10_01_01_01;
        maze[25] = 56'b01_01_01_10_01_01_10_01_01_10_01_01_01_01_01_01_01_01_10_01_01_10_01_01_10_01_01_01;
        maze[26] = 56'b01_10_10_10_10_10_10_01_01_10_10_10_10_01_01_10_10_10_10_01_01_10_10_10_10_10_10_01;
        maze[27] = 56'b01_10_01_01_01_01_01_01_01_01_01_01_10_01_01_10_01_01_01_01_01_01_01_01_01_01_10_01;
        maze[28] = 56'b01_10_01_01_01_01_01_01_01_01_01_01_10_01_01_10_01_01_01_01_01_01_01_01_01_01_10_01;
        maze[29] = 56'b01_11_10_10_10_10_10_10_10_10_10_10_10_10_10_10_10_10_10_10_10_10_10_10_10_10_11_01;
        maze[30] = {28{2'b01}};
    end

    function automatic logic in_bounds;
        input logic [4:0] x;
        input logic [4:0] y;
        begin
            in_bounds = (x < 5'd28) && (y < 5'd31);
        end
    endfunction

    function automatic logic [5:0] bit_hi;
        input logic [4:0] x;
        begin
            bit_hi = 6'd55 - ({1'b0, x} << 1);
        end
    endfunction

    function automatic logic [1:0] tile_from_xy;
        input logic [4:0] x;
        input logic [4:0] y;
        begin
            if (in_bounds(x, y))
                tile_from_xy = maze[y][bit_hi(x) -: 2];
            else
                tile_from_xy = WALL_TILE;
        end
    endfunction

    always_comb begin
        tile_a = tile_from_xy(x_a, y_a);
        tile_b = tile_from_xy(x_b, y_b);

        can_move_a = (tile_a != WALL_TILE);
        can_move_b = (tile_b != WALL_TILE);
    end

endmodule

Pacman_FPGA/testbench/initial_maze_rom_tb.sv
`timescale 1ns/1ps

module initial_maze_rom_tb;

    logic [4:0] x_a, y_a, x_b, y_b;
    logic [1:0] tile_a, tile_b;
    logic       can_move_a, can_move_b;

    int pass_count;
    int fail_count;

    localparam logic [1:0] PATH_TILE  = 2'b00;
    localparam logic [1:0] WALL_TILE  = 2'b01;
    localparam logic [1:0] PELLET     = 2'b10;
    localparam logic [1:0] POWER_TILE = 2'b11;

    initial_maze_rom dut (
        .x_a(x_a),
        .y_a(y_a),
        .tile_a(tile_a),
        .can_move_a(can_move_a),
        .x_b(x_b),
        .y_b(y_b),
        .tile_b(tile_b),
        .can_move_b(can_move_b)
    );

    task automatic check(input string name, input logic cond);
        if (cond) begin
            pass_count++;
            $display("PASS: %s", name);
        end else begin
            fail_count++;
            $display("FAIL: %s (tile_a=%b can_a=%b tile_b=%b can_b=%b)",
                     name, tile_a, can_move_a, tile_b, can_move_b);
        end
    endtask

    initial begin
        pass_count = 0;
        fail_count = 0;
        x_a = '0; y_a = '0;
        x_b = '0; y_b = '0;

        $dumpfile("waves/initial_maze_rom.vcd");
        $dumpvars(0, initial_maze_rom_tb);

        #1;

        // Outer wall row / corners
        x_a = 5'd0;  y_a = 5'd0;
        x_b = 5'd27; y_b = 5'd30;
        #1;
        check("corner (0,0) wall", tile_a === WALL_TILE && can_move_a === 1'b0);
        check("corner (27,30) wall", tile_b === WALL_TILE && can_move_b === 1'b0);

        // Pellet corridor on row 1
        x_a = 5'd1; y_a = 5'd1;
        #1;
        check("pellet at (1,1)", tile_a === PELLET && can_move_a === 1'b1);

        // Power pellets at (1,4) and (26,4)
        x_a = 5'd1;  y_a = 5'd4;
        x_b = 5'd26; y_b = 5'd4;
        #1;
        check("power pellet (1,4)", tile_a === POWER_TILE && can_move_a === 1'b1);
        check("power pellet (26,4)", tile_b === POWER_TILE && can_move_b === 1'b1);

        // Empty path in ghost house (row 14 tunnel / house empties)
        x_a = 5'd13; y_a = 5'd14;
        #1;
        check("house empty path tile", tile_a === PATH_TILE);

        // Pac-Man port blocks ghost-house door tiles (13,12) and (14,12)
        x_a = 5'd13; y_a = 5'd12;
        #1;
        check("pac door (13,12) blocked", can_move_a === 1'b0);
        x_a = 5'd14; y_a = 5'd12;
        #1;
        check("pac door (14,12) blocked",
              (tile_a !== WALL_TILE) && (can_move_a === 1'b0));

        // Ghost port blocks side house walls x=12 and x=15 for y in [12,16]
        x_a = 5'd6;  y_a = 5'd14;  // open tunnel for contrast on port A
        x_b = 5'd12; y_b = 5'd14;
        #1;
        check("ghost side wall (12,14) blocked on B", can_move_b === 1'b0);
        check("open path still free on A", can_move_a === 1'b1);

        x_b = 5'd15; y_b = 5'd16;
        #1;
        check("ghost side wall (15,16) blocked on B", can_move_b === 1'b0);

        // Dual-port independence
        x_a = 5'd1;  y_a = 5'd1;
        x_b = 5'd0;  y_b = 5'd0;
        #1;
        check("port A pellet while B wall",
              tile_a === PELLET && tile_b === WALL_TILE);

        // Out of bounds -> wall
        x_a = 5'd28; y_a = 5'd0;
        x_b = 5'd0;  y_b = 5'd31;
        #1;
        check("oob x wall", tile_a === WALL_TILE && can_move_a === 1'b0);
        check("oob y wall", tile_b === WALL_TILE && can_move_b === 1'b0);

        $display("\ninitial_maze_rom_tb: %0d PASS, %0d FAIL", pass_count, fail_count);
        $finish;
    end

endmodule

Pacman_FPGA/waves/initial_maze_rom.vcd
$date
	Sat Aug  1 00:16:17 2026
$end
$version
	Icarus Verilog
$end
$timescale
	1ps
$end
$scope module initial_maze_rom_tb $end
$var wire 2 ! tile_b [1:0] $end
$var wire 2 " tile_a [1:0] $end
$var wire 1 # can_move_b $end
$var wire 1 $ can_move_a $end
$var parameter 2 % PATH_TILE $end
$var parameter 2 & PELLET $end
$var parameter 2 ' POWER_TILE $end
$var parameter 2 ( WALL_TILE $end
$var reg 5 ) x_a [4:0] $end
$var reg 5 * x_b [4:0] $end
$var reg 5 + y_a [4:0] $end
$var reg 5 , y_b [4:0] $end
$var integer 32 - fail_count [31:0] $end
$var integer 32 . pass_count [31:0] $end
$scope module dut $end
$var wire 5 / x_a [4:0] $end
$var wire 5 0 x_b [4:0] $end
$var wire 5 1 y_a [4:0] $end
$var wire 5 2 y_b [4:0] $end
$var parameter 2 3 PATH_TILE $end
$var parameter 2 4 PELLET $end
$var parameter 2 5 POWER_TILE $end
$var parameter 2 6 WALL_TILE $end
$var reg 1 $ can_move_a $end
$var reg 1 # can_move_b $end
$var reg 2 7 tile_a [1:0] $end
$var reg 2 8 tile_b [1:0] $end
$scope function in_bounds $end
$upscope $end
$scope function tile_from_xy $end
$upscope $end
$upscope $end
$scope task check $end
$upscope $end
$upscope $end
$enddefinitions $end
$comment Show the parameter values. $end
$dumpall
b1 6
b11 5
b10 4
b0 3
b1 (
b11 '
b10 &
b0 %
$end
#0
$dumpvars
b1 8
b1 7
b0 2
b0 1
b0 0
b0 /
b0 .
b0 -
b0 ,
b0 +
b0 *
b0 )
0$
0#
b1 "
b1 !
$end
#1000
b11110 ,
b11110 2
b11011 *
b11011 0
#2000
1$
b10 "
b10 7
b1 +
b1 1
b1 )
b1 /
b10 .
#3000
1#
b11 !
b11 8
b11 "
b11 7
b100 ,
b100 2
b11010 *
b11010 0
b100 +
b100 1
b11 .
#4000
b0 "
b0 7
b1110 +
b1110 1
b1101 )
b1101 /
b101 .
#5000
0$
b1100 +
b1100 1
b110 .
#6000
b1110 )
b1110 /
b111 .
#7000
0#
1$
b0 !
b0 8
b10 "
b10 7
b1110 ,
b1110 2
b1100 *
b1100 0
b1110 +
b1110 1
b110 )
b110 /
b1000 .
#8000
b1 !
b1 8
b10000 ,
b10000 2
b1111 *
b1111 0
b1010 .
#9000
b0 ,
b0 2
b0 *
b0 0
b1 +
b1 1
b1 )
b1 /
b1011 .
#10000
0$
b1 "
b1 7
b11111 ,
b11111 2
b0 +
b0 1
b11100 )
b11100 /
b1100 .
#11000
b1110 .
