Pacman_FPGA/source/maze_wall_pellet_rom.sv
module maze_wall_pellet_rom (
    input  logic [4:0] x,
    input  logic [4:0] y,

    output logic [1:0] tile,
    output logic       collectible,
    output logic [7:0] pellet_index,

    output logic       can_move_pac,
    output logic       can_move_ghost
);

    localparam logic [1:0] PATH_TILE  = 2'b00;
    localparam logic [1:0] WALL_TILE  = 2'b01;
    localparam logic [1:0] PELLET     = 2'b10;
    localparam logic [1:0] POWER_TILE = 2'b11;

    // 24 tiles × 2 bits = 48 bits per row.
    // x = 0 is stored in bits [47:46].
    function automatic logic [47:0] row_data (
        input logic [4:0] yy
    );
        begin
            case (yy)
                5'd0:  row_data = 48'b01_01_01_01_01_01_01_01_01_01_01_01_01_01_01_01_01_01_01_01_01_01_01_01;
                5'd1:  row_data = 48'b01_10_10_10_10_10_10_10_10_10_10_01_01_10_10_10_10_10_10_10_10_10_10_01;
                5'd2:  row_data = 48'b01_10_01_01_10_01_01_01_01_01_10_01_01_10_01_01_01_01_01_10_01_01_10_01;
                5'd3:  row_data = 48'b01_10_01_01_10_01_01_01_01_01_10_01_01_10_01_01_01_01_01_10_01_01_10_01;
                5'd4:  row_data = 48'b01_11_10_10_10_10_10_10_10_10_10_10_10_10_10_10_10_10_10_10_10_10_11_01;
                5'd5:  row_data = 48'b01_10_01_01_10_01_01_10_01_01_01_01_01_01_01_01_10_01_01_10_01_01_10_01;
                5'd6:  row_data = 48'b01_10_01_01_10_01_01_10_01_01_01_01_01_01_01_01_10_01_01_10_01_01_10_01;
                5'd7:  row_data = 48'b01_10_10_10_10_01_01_10_10_10_10_01_01_10_10_10_10_01_01_10_10_10_10_01;
                5'd8:  row_data = 48'b01_01_01_01_10_01_01_01_01_01_10_01_01_10_01_01_01_01_01_10_01_01_01_01;
                5'd9:  row_data = 48'b01_01_01_01_10_01_01_01_01_01_10_01_01_10_01_01_01_01_01_10_01_01_01_01;
                5'd10: row_data = 48'b01_01_01_01_10_01_01_00_00_00_00_00_00_00_00_00_00_01_01_10_01_01_01_01;
                5'd11: row_data = 48'b01_01_01_01_10_01_01_00_01_01_01_00_00_01_01_01_00_01_01_10_01_01_01_01;
                5'd12: row_data = 48'b01_01_01_01_10_01_01_00_01_00_00_00_00_00_00_01_00_01_01_10_01_01_01_01;
                5'd13: row_data = 48'b00_00_00_00_10_00_00_00_01_00_00_00_00_00_00_01_00_00_00_10_00_00_00_00;
                5'd14: row_data = 48'b01_01_01_01_10_01_01_00_01_00_00_00_00_00_00_01_00_01_01_10_01_01_01_01;
                5'd15: row_data = 48'b01_01_01_01_10_01_01_00_01_01_01_01_01_01_01_01_00_01_01_10_01_01_01_01;
                5'd16: row_data = 48'b01_10_10_10_10_10_10_10_10_10_10_01_01_10_10_10_10_10_10_10_10_10_10_01;
                5'd17: row_data = 48'b01_10_01_01_10_01_01_01_01_01_10_01_01_10_01_01_01_01_01_10_01_01_10_01;
                5'd18: row_data = 48'b01_10_01_01_10_01_01_01_01_01_10_01_01_10_01_01_01_01_01_10_01_01_10_01;
                5'd19: row_data = 48'b01_11_10_10_10_10_10_10_10_10_10_10_10_10_10_10_10_10_10_10_10_10_11_01;
                5'd20: row_data = 48'b01_10_01_01_01_01_01_01_01_01_10_01_01_10_01_01_01_01_01_01_01_01_10_01;
                5'd21: row_data = 48'b01_10_01_01_01_01_01_01_01_01_10_01_01_10_01_01_01_01_01_01_01_01_10_01;
                5'd22: row_data = 48'b01_10_10_10_10_10_10_10_10_10_10_10_10_10_10_10_10_10_10_10_10_10_10_01;
                5'd23: row_data = 48'b01_01_01_01_01_01_01_01_01_01_01_01_01_01_01_01_01_01_01_01_01_01_01_01;
                default: row_data = {24{WALL_TILE}};
            endcase
        end
    endfunction

    // Number of collectibles in all rows before the selected row.
    // Total number of collectibles = 186.
    function automatic logic [7:0] row_base (
        input logic [4:0] yy
    );
        begin
            case (yy)
                5'd0:  row_base =   8'd0;
                5'd1:  row_base =   8'd0;
                5'd2:  row_base =   8'd20;
                5'd3:  row_base =   8'd26;
                5'd4:  row_base =   8'd32;
                5'd5:  row_base =   8'd54;
                5'd6:  row_base =   8'd60;
                5'd7:  row_base =   8'd66;
                5'd8:  row_base =   8'd82;
                5'd9:  row_base =   8'd86;
                5'd10: row_base =   8'd90;
                5'd11: row_base =   8'd92;
                5'd12: row_base =   8'd94;
                5'd13: row_base =   8'd96;
                5'd14: row_base =   8'd98;
                5'd15: row_base =   8'd100;
                5'd16: row_base =   8'd102;
                5'd17: row_base =   8'd122;
                5'd18: row_base =   8'd128;
                5'd19: row_base =   8'd134;
                5'd20: row_base =   8'd156;
                5'd21: row_base =   8'd160;
                5'd22: row_base =   8'd164;
                5'd23: row_base =   8'd186;
                default: row_base = 8'd0;
            endcase
        end
    endfunction

    function automatic logic in_bounds (
        input logic [4:0] xx,
        input logic [4:0] yy
    );
        begin
            in_bounds = (xx < 5'd24) && (yy < 5'd24);
        end
    endfunction

    logic [47:0] row;

    // One bit per column:
    // 1 means the column contains a pellet or power pellet.
    logic [23:0] collect_mask;

    // Contains only collectibles strictly left of x.
    logic [23:0] prefix_mask;

    // Max 22 collectibles per row, so 5 bits is enough; use 8 to match
    // pellet_index width and avoid wrap when adding into row_base.
    logic [7:0] prefix_count;

    always_comb begin
        row = row_data(y);

        collect_mask = 24'd0;
        prefix_mask  = 24'd0;
        prefix_count = 8'd0;

        // The MSB of each tile is 1 for both 10 and 11.
        for (int i = 0; i < 24; i++) begin
            collect_mask[i] = row[47 - 2*i];
        end

        // Keep only collectible columns to the left of x.
        for (int i = 0; i < 24; i++) begin
            if (i < x)
                prefix_mask[i] = collect_mask[i];
            else
                prefix_mask[i] = 1'b0;
        end

        // Count collectibles to the left.
        for (int i = 0; i < 24; i++) begin
            prefix_count = prefix_count + {7'b0, prefix_mask[i]};
        end

        if (in_bounds(x, y)) begin
            tile = row[(6'd47 - x*2) -: 2];

            pellet_index = row_base(y) + prefix_count;
        end else begin
            tile         = WALL_TILE;
            pellet_index = 8'd0;
        end

        collectible = tile[1];

        can_move_pac = (tile != WALL_TILE && (!(x == 11 && y == 12) && !(x == 12 && y == 12)));
        can_move_ghost = (tile != WALL_TILE && (!(x == 10 && (y >= 12 && y <= 14)) && !(x == 13 && (y >= 12 && y <= 14))));
    end
endmodule

Pacman_FPGA/testbench/maze_wall_pellet_rom_tb.sv
`timescale 1ns/1ps

module maze_wall_pellet_rom_tb;

    logic [4:0] x, y;
    logic [1:0] tile;
    logic       collectible;
    logic [7:0] pellet_index;
    logic       can_move_pac;
    logic       can_move_ghost;

    int pass_count;
    int fail_count;

    localparam logic [1:0] PATH_TILE  = 2'b00;
    localparam logic [1:0] WALL_TILE  = 2'b01;
    localparam logic [1:0] PELLET     = 2'b10;
    localparam logic [1:0] POWER_TILE = 2'b11;

    maze_wall_pellet_rom dut (
        .x(x),
        .y(y),
        .tile(tile),
        .collectible(collectible),
        .pellet_index(pellet_index),
        .can_move_pac(can_move_pac),
        .can_move_ghost(can_move_ghost)
    );

    task automatic check(input string name, input logic cond);
        if (cond) begin
            pass_count++;
            $display("PASS: %s", name);
        end else begin
            fail_count++;
            $display("FAIL: %s (x=%0d y=%0d tile=%b idx=%0d)", name, x, y, tile, pellet_index);
        end
    endtask

    initial begin
        pass_count = 0;
        fail_count = 0;
        x = 5'd0;
        y = 5'd0;

        $dumpfile("waves/maze_wall_pellet_rom.vcd");
        $dumpvars(0, maze_wall_pellet_rom_tb);

        #1;
        check("corner wall", tile === WALL_TILE && !collectible);

        // Bottom row has 22 pellets; left/right must not share indices.
        y = 5'd22;
        x = 5'd1;
        #1;
        check("bottom-left pellet", tile === PELLET && collectible);
        check("bottom-left index base", pellet_index === 8'd164);

        x = 5'd17;
        #1;
        check("bottom x=17 distinct from x=1", pellet_index === 8'd180);

        x = 5'd22;
        #1;
        check("bottom-right last index", pellet_index === 8'd185);

        // Power pellets on row 19 corners.
        y = 5'd19;
        x = 5'd1;
        #1;
        check("power pellet bottom-left", tile === POWER_TILE && collectible);

        x = 5'd22;
        #1;
        check("power pellet bottom-right", tile === POWER_TILE && collectible);
        check("power right index unique", pellet_index === 8'd155);

        // OOB
        x = 5'd24;
        y = 5'd0;
        #1;
        check("oob is wall", tile === WALL_TILE && pellet_index === 8'd0);

        // Ghost house door tiles blocked for pac.
        x = 5'd11;
        y = 5'd12;
        #1;
        check("ghost door blocks pac", can_move_pac === 1'b0);

        $display("\nmaze_wall_pellet_rom_tb: %0d PASS, %0d FAIL", pass_count, fail_count);
        if (fail_count != 0) $fatal(1);
        $finish;
    end

endmodule

Pacman_FPGA/waves/maze_wall_pellet_rom.vcd
$date
	Sat Aug  1 22:09:52 2026
$end
$version
	Icarus Verilog
$end
$timescale
	1ps
$end
$scope module maze_wall_pellet_rom_tb $end
$var wire 2 ! tile [1:0] $end
$var wire 8 " pellet_index [7:0] $end
$var wire 1 # collectible $end
$var wire 1 $ can_move_pac $end
$var wire 1 % can_move_ghost $end
$var parameter 2 & PATH_TILE $end
$var parameter 2 ' PELLET $end
$var parameter 2 ( POWER_TILE $end
$var parameter 2 ) WALL_TILE $end
$var reg 5 * x [4:0] $end
$var reg 5 + y [4:0] $end
$var integer 32 , fail_count [31:0] $end
$var integer 32 - pass_count [31:0] $end
$scope module dut $end
$var wire 5 . x [4:0] $end
$var wire 5 / y [4:0] $end
$var parameter 2 0 PATH_TILE $end
$var parameter 2 1 PELLET $end
$var parameter 2 2 POWER_TILE $end
$var parameter 2 3 WALL_TILE $end
$var reg 1 % can_move_ghost $end
$var reg 1 $ can_move_pac $end
$var reg 24 4 collect_mask [23:0] $end
$var reg 1 # collectible $end
$var reg 8 5 pellet_index [7:0] $end
$var reg 8 6 prefix_count [7:0] $end
$var reg 24 7 prefix_mask [23:0] $end
$var reg 48 8 row [47:0] $end
$var reg 2 9 tile [1:0] $end
$scope function in_bounds $end
$upscope $end
$scope function row_base $end
$upscope $end
$scope function row_data $end
$upscope $end
$scope begin $ivl_for_loop0 $end
$var integer 32 : i [31:0] $end
$upscope $end
$scope begin $ivl_for_loop1 $end
$var integer 32 ; i [31:0] $end
$upscope $end
$scope begin $ivl_for_loop2 $end
$var integer 32 < i [31:0] $end
$upscope $end
$upscope $end
$scope task check $end
$upscope $end
$upscope $end
$enddefinitions $end
$comment Show the parameter values. $end
$dumpall
b1 3
b11 2
b10 1
b0 0
b1 )
b11 (
b10 '
b0 &
$end
#0
$dumpvars
b11000 <
b11000 ;
b11000 :
b1 9
b10101010101010101010101010101010101010101010101 8
b0 7
b0 6
b0 5
b0 4
b0 /
b0 .
b0 -
b0 ,
b0 +
b0 *
0%
0$
0#
b0 "
b1 !
$end
#1000
1%
1$
1#
b10100100 "
b10100100 5
b10 !
b10 9
b11000 <
b11000 ;
b11111111111111111111110 4
b11000 :
b11010101010101010101010101010101010101010101001 8
b1 *
b1 .
b10110 +
b10110 /
b1 -
#2000
b10110100 "
b10110100 5
b10000 6
b11000 <
b11111111111111110 7
b11000 ;
b11000 :
b11111111111111111111110 4
b10001 *
b10001 .
b11 -
#3000
b10111001 "
b10111001 5
b11000 <
b11000 ;
b11000 :
b10101 6
b1111111111111111111110 7
b11111111111111111111110 4
b10110 *
b10110 .
b100 -
#4000
b10000110 "
b10000110 5
b11 !
b11 9
b11000 <
b11000 ;
b11000 :
b0 6
b0 7
b11111111111111111111110 4
b11110101010101010101010101010101010101010101101 8
b1 *
b1 .
b10011 +
b10011 /
b101 -
#5000
b10011011 "
b10011011 5
b10101 6
b11000 <
b1111111111111111111110 7
b11000 ;
b11000 :
b11111111111111111111110 4
b10110 *
b10110 .
b110 -
#6000
0%
0$
0#
b0 "
b0 5
b1 !
b1 9
b11000 <
b11000 ;
b11000 :
b0 6
b0 7
b0 4
b10101010101010101010101010101010101010101010101 8
b0 +
b0 /
b11000 *
b11000 .
b1000 -
#7000
1%
b1011111 "
b1011111 5
b0 !
b0 9
b1 6
b11000 <
b10000 7
b11000 ;
b10000000000000010000 4
b11000 :
b10101011001010001000000000000010001011001010101 8
b1100 +
b1100 /
b1011 *
b1011 .
b1001 -
#8000
b1010 -
