Pacman_FPGA/source/maze_bram.sv
module maze_bram (
    input  logic       clk,
    input  logic       reset,

    input  logic       map_rst,
    output logic       map_loaded,

    // VGA read port
    input  logic [4:0] x_vga,
    input  logic [4:0] y_vga,
    output logic [1:0] rdata_vga,

    // Central/game read-write port
    input  logic [4:0] x_central,
    input  logic [4:0] y_central,
    input  logic       write_en,
    output logic [1:0] rdata_central,

    // Reload source ROM interface
    output logic [4:0] rom_x,
    output logic [4:0] rom_y,
    input  logic [1:0] rom_data
);

    // Tile encodings
    localparam logic [1:0] PATH_TILE  = 2'b00;
    localparam logic [1:0] WALL_TILE  = 2'b01;
    localparam logic [1:0] PELLET     = 2'b10;
    localparam logic [1:0] POWER_TILE = 2'b11;

    localparam logic [7:0] WALL_WORD = {4{WALL_TILE}};

    // ------------------------------------------------------------------
    // The array itself. Everything below is written so that the ONLY
    // things ever driving mem[] are: one write process with a single
    // enable/address/data mux, and read processes that load from mem[]
    // under a single enable with no alternate data source. All "force
    // WALL_TILE" / invalid handling lives in separate small valid-flags
    // or the combinational output mux, never mixed into the same
    // register as the memory read/write data.
    // ------------------------------------------------------------------
    logic [7:0] mem [0:255];

    // ---------------- Reload (ROM -> RAM) control/counters ----------------
    logic [4:0] load_x;
    logic [4:0] load_y;

    logic [7:0] load_word_addr;
    logic [1:0] load_tile_sel;

    logic [7:0] pack_word;
    logic [7:0] next_pack_word;

    assign rom_x = load_x;
    assign rom_y = load_y;

    always_comb begin
        next_pack_word = pack_word;

        case (load_tile_sel)
            2'd0:    next_pack_word[1:0] = rom_data;
            2'd1:    next_pack_word[3:2] = rom_data;
            2'd2:    next_pack_word[5:4] = rom_data;
            2'd3:    next_pack_word[7:6] = rom_data;
            default: next_pack_word = pack_word;
        endcase
    end

    // Reload/control counters only. No mem[] access here at all -
    // async reset on this block is fine, since it never touches
    // memory data, only control state.
    always_ff @(posedge clk or posedge reset) begin
        if (reset) begin
            map_loaded     <= 1'b0;
            load_x         <= 5'd0;
            load_y         <= 5'd0;
            load_word_addr <= 8'd0;
            load_tile_sel  <= 2'd0;
            pack_word      <= 8'd0;
        end else if (map_rst) begin
            map_loaded     <= 1'b0;
            load_x         <= 5'd0;
            load_y         <= 5'd0;
            load_word_addr <= 8'd0;
            load_tile_sel  <= 2'd0;
            pack_word      <= 8'd0;
        end else if (!map_loaded) begin
            if (load_tile_sel == 2'd3) begin
                pack_word     <= 8'd0;
                load_tile_sel <= 2'd0;

                if (load_word_addr == 8'd216) begin
                    map_loaded <= 1'b1;
                end else begin
                    load_word_addr <= load_word_addr + 8'd1;
                end
            end else begin
                pack_word     <= next_pack_word;
                load_tile_sel <= load_tile_sel + 2'd1;
            end

            if (load_x == 5'd27) begin
                load_x <= 5'd0;
                if (load_y != 5'd30) load_y <= load_y + 5'd1;
            end else begin
                load_x <= load_x + 5'd1;
            end
        end
    end

    // ---------------- VGA read address calc ----------------
    logic       vga_in_bounds;
    logic [9:0] vga_tile_index;
    logic [7:0] vga_word_addr;
    logic [1:0] vga_tile_sel;

    assign vga_in_bounds  = (x_vga < 5'd28) && (y_vga < 5'd31);
    assign vga_tile_index = ({5'd0, y_vga} * 10'd28) + {5'd0, x_vga};
    assign vga_word_addr  = vga_tile_index[9:2];
    assign vga_tile_sel   = vga_tile_index[1:0];

    // ---------------- Central read/write address calc ----------------
    logic       central_in_bounds;
    logic [9:0] central_tile_index;
    logic [7:0] central_word_addr;
    logic [1:0] central_tile_sel;

    assign central_in_bounds  = (x_central < 5'd28) && (y_central < 5'd31);
    assign central_tile_index = ({5'd0, y_central} * 10'd28) + {5'd0, x_central};
    assign central_word_addr  = central_tile_index[9:2];
    assign central_tile_sel   = central_tile_index[1:0];

    // ---------------- Single, simple write port into mem[] ----------------
    // Exactly one enable, one address mux, one data mux - each mutually
    // exclusive by construction (reload vs. gameplay-write), collapsed
    // combinationally so the memory write process itself is a plain
    // "if (we) mem[addr] <= data;".
    logic [7:0] central_addr_q;
    logic       central_valid_q;
    logic [7:0] central_cleared_word;

    logic       mem_we;
    logic [7:0] mem_waddr;
    logic [7:0] mem_wdata;

    assign mem_we    = (!map_loaded && (load_tile_sel == 2'd3))
                        || (map_loaded && write_en && central_valid_q);
    assign mem_waddr = (!map_loaded) ? load_word_addr : central_addr_q;
    assign mem_wdata = (!map_loaded) ? next_pack_word : central_cleared_word;

    always_ff @(posedge clk) begin
        if (mem_we) mem[mem_waddr] <= mem_wdata;
    end

    // ---------------- VGA read port: single-source read register ----------------
    logic [7:0] vga_word_q;
    logic [1:0] vga_sel_q;
    logic       vga_valid_q;

    always_ff @(posedge clk) begin
        if (map_loaded && vga_in_bounds) begin
            vga_word_q <= mem[vga_word_addr];
            vga_sel_q  <= vga_tile_sel;
        end
    end

    always_ff @(posedge clk or posedge reset) begin
        if (reset) vga_valid_q <= 1'b0;
        else       vga_valid_q <= map_loaded && vga_in_bounds;
    end

    always_comb begin
        if (!vga_valid_q) begin
            rdata_vga = WALL_TILE;
        end else begin
            case (vga_sel_q)
                2'd0:    rdata_vga = vga_word_q[1:0];
                2'd1:    rdata_vga = vga_word_q[3:2];
                2'd2:    rdata_vga = vga_word_q[5:4];
                2'd3:    rdata_vga = vga_word_q[7:6];
                default: rdata_vga = WALL_TILE;
            endcase
        end
    end

    // ---------------- Central read port: single-source read register ----------------
    logic [7:0] central_word_q;
    logic [1:0] central_sel_q;

    always_ff @(posedge clk) begin
        if (map_loaded && central_in_bounds) begin
            central_word_q <= mem[central_word_addr];
            central_addr_q <= central_word_addr;
            central_sel_q  <= central_tile_sel;
        end
    end

    always_ff @(posedge clk or posedge reset) begin
        if (reset)      central_valid_q <= 1'b0;
        else if (map_rst) central_valid_q <= 1'b0;
        else            central_valid_q <= map_loaded && central_in_bounds;
    end

    always_comb begin
        central_cleared_word = central_word_q;
        case (central_sel_q)
            2'd0:    central_cleared_word[1:0] = PATH_TILE;
            2'd1:    central_cleared_word[3:2] = PATH_TILE;
            2'd2:    central_cleared_word[5:4] = PATH_TILE;
            2'd3:    central_cleared_word[7:6] = PATH_TILE;
            default: central_cleared_word = central_word_q;
        endcase
    end

    always_comb begin
        if (!central_valid_q) begin
            rdata_central = WALL_TILE;
        end else begin
            case (central_sel_q)
                2'd0:    rdata_central = central_word_q[1:0];
                2'd1:    rdata_central = central_word_q[3:2];
                2'd2:    rdata_central = central_word_q[5:4];
                2'd3:    rdata_central = central_word_q[7:6];
                default: rdata_central = WALL_TILE;
            endcase
        end
    end

endmodule

Pacman_FPGA/testbench/maze_bram_tb.sv
`timescale 1ns/1ps

module maze_bram_tb;

    logic       clk;
    logic       reset;
    logic       map_rst;
    logic       map_loaded;

    logic [4:0] x_vga;
    logic [4:0] y_vga;
    logic [1:0] rdata_vga;

    logic [4:0] x_central;
    logic [4:0] y_central;
    logic       write_en;
    logic [1:0] rdata_central;

    logic [4:0] rom_x;
    logic [4:0] rom_y;
    logic [1:0] rom_data;

    int pass_count;
    int fail_count;
    int timeout;

    localparam logic [1:0] PATH_TILE  = 2'b00;
    localparam logic [1:0] WALL_TILE  = 2'b01;
    localparam logic [1:0] PELLET     = 2'b10;
    localparam logic [1:0] POWER_TILE = 2'b11;

    // Deterministic ROM stub for reload
    always_comb begin
        if ((rom_x == 5'd5) && (rom_y == 5'd5))
            rom_data = PELLET;
        else if ((rom_x == 5'd6) && (rom_y == 5'd6))
            rom_data = POWER_TILE;
        else if ((rom_x == 5'd0) || (rom_y == 5'd0))
            rom_data = WALL_TILE;
        else
            rom_data = PATH_TILE;
    end

    maze_bram dut (
        .clk(clk),
        .reset(reset),
        .map_rst(map_rst),
        .map_loaded(map_loaded),
        .x_vga(x_vga),
        .y_vga(y_vga),
        .rdata_vga(rdata_vga),
        .x_central(x_central),
        .y_central(y_central),
        .write_en(write_en),
        .rdata_central(rdata_central),
        .rom_x(rom_x),
        .rom_y(rom_y),
        .rom_data(rom_data)
    );

    initial clk = 1'b0;
    always #5 clk = ~clk;

    task automatic check(input string name, input logic cond);
        if (cond) begin
            pass_count++;
            $display("PASS: %s", name);
        end else begin
            fail_count++;
            $display("FAIL: %s", name);
        end
    endtask

    task automatic tick(input int n = 1);
        repeat (n) @(posedge clk);
    endtask

    task automatic wait_loaded;
        timeout = 0;
        while (!map_loaded && timeout < 2000) begin
            @(posedge clk);
            timeout++;
        end
        check("map_loaded within timeout", map_loaded === 1'b1);
    endtask

    task automatic settle_central_read;
        // Address must be stable for two clocks after map_loaded
        tick(2);
    endtask

    initial begin
        pass_count = 0;
        fail_count = 0;
        reset      = 1'b1;
        map_rst    = 1'b0;
        write_en   = 1'b0;
        x_vga      = 5'd0;
        y_vga      = 5'd0;
        x_central  = 5'd0;
        y_central  = 5'd0;

        $dumpfile("waves/maze_bram.vcd");
        $dumpvars(0, maze_bram_tb);

        tick(2);
        reset = 1'b0;
        check("not loaded after reset", map_loaded === 1'b0);

        wait_loaded();

        // VGA in-bounds pellet tile
        x_vga = 5'd5;
        y_vga = 5'd5;
        tick(2);
        check("VGA reads pellet at (5,5)", rdata_vga === PELLET);

        // VGA wall on border
        x_vga = 5'd0;
        y_vga = 5'd3;
        tick(2);
        check("VGA reads wall at (0,3)", rdata_vga === WALL_TILE);

        // VGA path
        x_vga = 5'd4;
        y_vga = 5'd4;
        tick(2);
        check("VGA reads path at (4,4)", rdata_vga === PATH_TILE);

        // VGA OOB -> wall (valid flag low)
        x_vga = 5'd28;
        y_vga = 5'd0;
        tick(2);
        check("VGA OOB returns wall", rdata_vga === WALL_TILE);

        // Central read pellet, then clear
        x_central = 5'd5;
        y_central = 5'd5;
        settle_central_read();
        check("central pellet before clear", rdata_central === PELLET);

        write_en = 1'b1;
        tick(1);
        write_en = 1'b0;
        settle_central_read();
        check("central pellet cleared to path", rdata_central === PATH_TILE);

        // Central power tile
        x_central = 5'd6;
        y_central = 5'd6;
        settle_central_read();
        check("central power tile", rdata_central === POWER_TILE);

        write_en = 1'b1;
        tick(1);
        write_en = 1'b0;
        settle_central_read();
        check("central power cleared to path", rdata_central === PATH_TILE);

        // Central OOB
        x_central = 5'd31;
        y_central = 5'd0;
        tick(2);
        check("central OOB returns wall", rdata_central === WALL_TILE);

        // map_rst reloads
        map_rst = 1'b1;
        tick(1);
        map_rst = 1'b0;
        check("map_rst clears map_loaded", map_loaded === 1'b0);
        wait_loaded();

        x_central = 5'd5;
        y_central = 5'd5;
        settle_central_read();
        check("pellet restored after reload", rdata_central === PELLET);

        $display("\nmaze_bram_tb: %0d PASS, %0d FAIL", pass_count, fail_count);
        $finish;
    end

endmodule

Pacman_FPGA/waves/maze_bram.vcd
$date
	Fri Jul 24 16:24:15 2026
$end
$version
	Icarus Verilog
$end
$timescale
	1ps
$end
$scope module maze_bram_tb $end
$var wire 5 ! rom_y [4:0] $end
$var wire 5 " rom_x [4:0] $end
$var wire 2 # rdata_vga [1:0] $end
$var wire 2 $ rdata_central [1:0] $end
$var wire 1 % map_loaded $end
$var parameter 2 & PATH_TILE $end
$var parameter 2 ' PELLET $end
$var parameter 2 ( POWER_TILE $end
$var parameter 2 ) WALL_TILE $end
$var reg 1 * clk $end
$var reg 1 + map_rst $end
$var reg 1 , reset $end
$var reg 2 - rom_data [1:0] $end
$var reg 1 . write_en $end
$var reg 5 / x_central [4:0] $end
$var reg 5 0 x_vga [4:0] $end
$var reg 5 1 y_central [4:0] $end
$var reg 5 2 y_vga [4:0] $end
$var integer 32 3 fail_count [31:0] $end
$var integer 32 4 pass_count [31:0] $end
$var integer 32 5 timeout [31:0] $end
$scope module dut $end
$var wire 1 6 central_in_bounds $end
$var wire 1 * clk $end
$var wire 1 + map_rst $end
$var wire 1 7 mem_we $end
$var wire 1 , reset $end
$var wire 2 8 rom_data [1:0] $end
$var wire 5 9 rom_x [4:0] $end
$var wire 5 : rom_y [4:0] $end
$var wire 1 ; vga_in_bounds $end
$var wire 1 . write_en $end
$var wire 5 < x_central [4:0] $end
$var wire 5 = x_vga [4:0] $end
$var wire 5 > y_central [4:0] $end
$var wire 5 ? y_vga [4:0] $end
$var wire 8 @ vga_word_addr [7:0] $end
$var wire 2 A vga_tile_sel [1:0] $end
$var wire 10 B vga_tile_index [9:0] $end
$var wire 8 C mem_wdata [7:0] $end
$var wire 8 D mem_waddr [7:0] $end
$var wire 8 E central_word_addr [7:0] $end
$var wire 2 F central_tile_sel [1:0] $end
$var wire 10 G central_tile_index [9:0] $end
$var parameter 2 H PATH_TILE $end
$var parameter 2 I PELLET $end
$var parameter 2 J POWER_TILE $end
$var parameter 2 K WALL_TILE $end
$var parameter 8 L WALL_WORD $end
$var reg 8 M central_addr_q [7:0] $end
$var reg 8 N central_cleared_word [7:0] $end
$var reg 2 O central_sel_q [1:0] $end
$var reg 1 P central_valid_q $end
$var reg 8 Q central_word_q [7:0] $end
$var reg 2 R load_tile_sel [1:0] $end
$var reg 8 S load_word_addr [7:0] $end
$var reg 5 T load_x [4:0] $end
$var reg 5 U load_y [4:0] $end
$var reg 1 % map_loaded $end
$var reg 8 V next_pack_word [7:0] $end
$var reg 8 W pack_word [7:0] $end
$var reg 2 X rdata_central [1:0] $end
$var reg 2 Y rdata_vga [1:0] $end
$var reg 2 Z vga_sel_q [1:0] $end
$var reg 1 [ vga_valid_q $end
$var reg 8 \ vga_word_q [7:0] $end
$upscope $end
$scope task check $end
$upscope $end
$scope task settle_central_read $end
$upscope $end
$scope task tick $end
$upscope $end
$scope task wait_loaded $end
$upscope $end
$upscope $end
$enddefinitions $end
$comment Show the parameter values. $end
$dumpall
b1010101 L
b1 K
b11 J
b10 I
b0 H
b1 )
b11 (
b10 '
b0 &
$end
#0
$dumpvars
bx \
0[
bx Z
b1 Y
b1 X
b0 W
b1 V
b0 U
b0 T
b0 S
b0 R
bx Q
0P
bx O
bx N
bx M
b0 G
b0 F
b0 E
b0 D
b1 C
b0 B
b0 A
b0 @
b0 ?
b0 >
b0 =
b0 <
1;
b0 :
b0 9
b1 8
07
16
b0 5
b0 4
b0 3
b0 2
b0 1
b0 0
b0 /
0.
b1 -
1,
0+
0*
0%
b1 $
b1 #
b0 "
b0 !
$end
#5000
1*
#10000
0*
#15000
b101 C
b101 V
b1 "
b1 9
b1 T
b1 R
b1 W
b1 4
0,
1*
#20000
0*
#25000
b10101 C
b10101 V
b10 "
b10 9
b10 T
b10 R
b101 W
b1 5
1*
#30000
0*
#35000
17
b1010101 C
b1010101 V
b11 "
b11 9
b11 T
b11 R
b10101 W
b10 5
1*
#40000
0*
#45000
07
b1 C
b1 D
b1 V
b100 "
b100 9
b100 T
b1 S
b0 R
b0 W
b11 5
1*
#50000
0*
#55000
b101 C
b101 V
b101 "
b101 9
b101 T
b1 R
b1 W
b100 5
1*
#60000
0*
#65000
b10101 C
b10101 V
b110 "
b110 9
b110 T
b10 R
b101 W
b101 5
1*
#70000
0*
#75000
17
b1010101 C
b1010101 V
b111 "
b111 9
b111 T
b11 R
b10101 W
b110 5
1*
#80000
0*
#85000
07
b1 C
b10 D
b1 V
b1000 "
b1000 9
b1000 T
b10 S
b0 R
b0 W
b111 5
1*
#90000
0*
#95000
b101 C
b101 V
b1001 "
b1001 9
b1001 T
b1 R
b1 W
b1000 5
1*
#100000
0*
#105000
b10101 C
b10101 V
b1010 "
b1010 9
b1010 T
b10 R
b101 W
b1001 5
1*
#110000
0*
#115000
17
b1010101 C
b1010101 V
b1011 "
b1011 9
b1011 T
b11 R
b10101 W
b1010 5
1*
#120000
0*
#125000
07
b1 C
b11 D
b1 V
b1100 "
b1100 9
b1100 T
b11 S
b0 R
b0 W
b1011 5
1*
#130000
0*
#135000
b101 C
b101 V
b1101 "
b1101 9
b1101 T
b1 R
b1 W
b1100 5
1*
#140000
0*
#145000
b10101 C
b10101 V
b1110 "
b1110 9
b1110 T
b10 R
b101 W
b1101 5
1*
#150000
0*
#155000
17
b1010101 C
b1010101 V
b1111 "
b1111 9
b1111 T
b11 R
b10101 W
b1110 5
1*
#160000
0*
#165000
07
b1 C
b100 D
b1 V
b10000 "
b10000 9
b10000 T
b100 S
b0 R
b0 W
b1111 5
1*
#170000
0*
#175000
b101 C
b101 V
b10001 "
b10001 9
b10001 T
b1 R
b1 W
b10000 5
1*
#180000
0*
#185000
b10101 C
b10101 V
b10010 "
b10010 9
b10010 T
b10 R
b101 W
b10001 5
1*
#190000
0*
#195000
17
b1010101 C
b1010101 V
b10011 "
b10011 9
b10011 T
b11 R
b10101 W
b10010 5
1*
#200000
0*
#205000
07
b1 C
b101 D
b1 V
b10100 "
b10100 9
b10100 T
b101 S
b0 R
b0 W
b10011 5
1*
#210000
0*
#215000
b101 C
b101 V
b10101 "
b10101 9
b10101 T
b1 R
b1 W
b10100 5
1*
#220000
0*
#225000
b10101 C
b10101 V
b10110 "
b10110 9
b10110 T
b10 R
b101 W
b10101 5
1*
#230000
0*
#235000
17
b1010101 C
b1010101 V
b10111 "
b10111 9
b10111 T
b11 R
b10101 W
b10110 5
1*
#240000
0*
#245000
07
b1 C
b110 D
b1 V
b11000 "
b11000 9
b11000 T
b110 S
b0 R
b0 W
b10111 5
1*
#250000
0*
#255000
b101 C
b101 V
b11001 "
b11001 9
b11001 T
b1 R
b1 W
b11000 5
1*
#260000
0*
#265000
b10101 C
b10101 V
b11010 "
b11010 9
b11010 T
b10 R
b101 W
b11001 5
1*
#270000
0*
#275000
17
b1010101 C
b1010101 V
b11011 "
b11011 9
b11011 T
b11 R
b10101 W
b11010 5
1*
#280000
0*
#285000
07
b1 C
b111 D
b1 V
b1 !
b1 :
b1 U
b0 "
b0 9
b0 T
b111 S
b0 R
b0 W
b11011 5
1*
#290000
0*
#295000
b1 C
b0 -
b0 8
b1 V
b1 "
b1 9
b1 T
b1 R
b1 W
b11100 5
1*
#300000
0*
#305000
b10 "
b10 9
b10 T
b10 R
b11101 5
1*
#310000
0*
#315000
17
b11 "
b11 9
b11 T
b11 R
b11110 5
1*
#320000
0*
#325000
07
b0 C
b1000 D
b0 V
b100 "
b100 9
b100 T
b1000 S
b0 R
b0 W
b11111 5
1*
#330000
0*
#335000
b101 "
b101 9
b101 T
b1 R
b100000 5
1*
#340000
0*
#345000
b110 "
b110 9
b110 T
b10 R
b100001 5
1*
#350000
0*
#355000
17
b111 "
b111 9
b111 T
b11 R
b100010 5
1*
#360000
0*
#365000
07
b1001 D
b1000 "
b1000 9
b1000 T
b1001 S
b0 R
b100011 5
1*
#370000
0*
#375000
b1001 "
b1001 9
b1001 T
b1 R
b100100 5
1*
#380000
0*
#385000
b1010 "
b1010 9
b1010 T
b10 R
b100101 5
1*
#390000
0*
#395000
17
b1011 "
b1011 9
b1011 T
b11 R
b100110 5
1*
#400000
0*
#405000
07
b1010 D
b1100 "
b1100 9
b1100 T
b1010 S
b0 R
b100111 5
1*
#410000
0*
#415000
b1101 "
b1101 9
b1101 T
b1 R
b101000 5
1*
#420000
0*
#425000
b1110 "
b1110 9
b1110 T
b10 R
b101001 5
1*
#430000
0*
#435000
17
b1111 "
b1111 9
b1111 T
b11 R
b101010 5
1*
#440000
0*
#445000
07
b1011 D
b10000 "
b10000 9
b10000 T
b1011 S
b0 R
b101011 5
1*
#450000
0*
#455000
b10001 "
b10001 9
b10001 T
b1 R
b101100 5
1*
#460000
0*
#465000
b10010 "
b10010 9
b10010 T
b10 R
b101101 5
1*
#470000
0*
#475000
17
b10011 "
b10011 9
b10011 T
b11 R
b101110 5
1*
#480000
0*
#485000
07
b1100 D
b10100 "
b10100 9
b10100 T
b1100 S
b0 R
b101111 5
1*
#490000
0*
#495000
b10101 "
b10101 9
b10101 T
b1 R
b110000 5
1*
#500000
0*
#505000
b10110 "
b10110 9
b10110 T
b10 R
b110001 5
1*
#510000
0*
#515000
17
b10111 "
b10111 9
b10111 T
b11 R
b110010 5
1*
#520000
0*
#525000
07
b1101 D
b11000 "
b11000 9
b11000 T
b1101 S
b0 R
b110011 5
1*
#530000
0*
#535000
b11001 "
b11001 9
b11001 T
b1 R
b110100 5
1*
#540000
0*
#545000
b11010 "
b11010 9
b11010 T
b10 R
b110101 5
1*
#550000
0*
#555000
17
b11011 "
b11011 9
b11011 T
b11 R
b110110 5
1*
#560000
0*
#565000
b1 C
b1 V
07
b1 -
b1 8
b1110 D
b10 !
b10 :
b10 U
b0 "
b0 9
b0 T
b1110 S
b0 R
b110111 5
1*
#570000
0*
#575000
b1 C
b0 -
b0 8
b1 V
b1 "
b1 9
b1 T
b1 R
b1 W
b111000 5
1*
#580000
0*
#585000
b10 "
b10 9
b10 T
b10 R
b111001 5
1*
#590000
0*
#595000
17
b11 "
b11 9
b11 T
b11 R
b111010 5
1*
#600000
0*
#605000
07
b0 C
b1111 D
b0 V
b100 "
b100 9
b100 T
b1111 S
b0 R
b0 W
b111011 5
1*
#610000
0*
#615000
b101 "
b101 9
b101 T
b1 R
b111100 5
1*
#620000
0*
#625000
b110 "
b110 9
b110 T
b10 R
b111101 5
1*
#630000
0*
#635000
17
b111 "
b111 9
b111 T
b11 R
b111110 5
1*
#640000
0*
#645000
07
b10000 D
b1000 "
b1000 9
b1000 T
b10000 S
b0 R
b111111 5
1*
#650000
0*
#655000
b1001 "
b1001 9
b1001 T
b1 R
b1000000 5
1*
#660000
0*
#665000
b1010 "
b1010 9
b1010 T
b10 R
b1000001 5
1*
#670000
0*
#675000
17
b1011 "
b1011 9
b1011 T
b11 R
b1000010 5
1*
#680000
0*
#685000
07
b10001 D
b1100 "
b1100 9
b1100 T
b10001 S
b0 R
b1000011 5
1*
#690000
0*
#695000
b1101 "
b1101 9
b1101 T
b1 R
b1000100 5
1*
#700000
0*
#705000
b1110 "
b1110 9
b1110 T
b10 R
b1000101 5
1*
#710000
0*
#715000
17
b1111 "
b1111 9
b1111 T
b11 R
b1000110 5
1*
#720000
0*
#725000
07
b10010 D
b10000 "
b10000 9
b10000 T
b10010 S
b0 R
b1000111 5
1*
#730000
0*
#735000
b10001 "
b10001 9
b10001 T
b1 R
b1001000 5
1*
#740000
0*
#745000
b10010 "
b10010 9
b10010 T
b10 R
b1001001 5
1*
#750000
0*
#755000
17
b10011 "
b10011 9
b10011 T
b11 R
b1001010 5
1*
#760000
0*
#765000
07
b10011 D
b10100 "
b10100 9
b10100 T
b10011 S
b0 R
b1001011 5
1*
#770000
0*
#775000
b10101 "
b10101 9
b10101 T
b1 R
b1001100 5
1*
#780000
0*
#785000
b10110 "
b10110 9
b10110 T
b10 R
b1001101 5
1*
#790000
0*
#795000
17
b10111 "
b10111 9
b10111 T
b11 R
b1001110 5
1*
#800000
0*
#805000
07
b10100 D
b11000 "
b11000 9
b11000 T
b10100 S
b0 R
b1001111 5
1*
#810000
0*
#815000
b11001 "
b11001 9
b11001 T
b1 R
b1010000 5
1*
#820000
0*
#825000
b11010 "
b11010 9
b11010 T
b10 R
b1010001 5
1*
#830000
0*
#835000
17
b11011 "
b11011 9
b11011 T
b11 R
b1010010 5
1*
#840000
0*
#845000
b1 C
b1 V
07
b1 -
b1 8
b10101 D
b11 !
b11 :
b11 U
b0 "
b0 9
b0 T
b10101 S
b0 R
b1010011 5
1*
#850000
0*
#855000
b1 C
b0 -
b0 8
b1 V
b1 "
b1 9
b1 T
b1 R
b1 W
b1010100 5
1*
#860000
0*
#865000
b10 "
b10 9
b10 T
b10 R
b1010101 5
1*
#870000
0*
#875000
17
b11 "
b11 9
b11 T
b11 R
b1010110 5
1*
#880000
0*
#885000
07
b0 C
b10110 D
b0 V
b100 "
b100 9
b100 T
b10110 S
b0 R
b0 W
b1010111 5
1*
#890000
0*
#895000
b101 "
b101 9
b101 T
b1 R
b1011000 5
1*
#900000
0*
#905000
b110 "
b110 9
b110 T
b10 R
b1011001 5
1*
#910000
0*
#915000
17
b111 "
b111 9
b111 T
b11 R
b1011010 5
1*
#920000
0*
#925000
07
b10111 D
b1000 "
b1000 9
b1000 T
b10111 S
b0 R
b1011011 5
1*
#930000
0*
#935000
b1001 "
b1001 9
b1001 T
b1 R
b1011100 5
1*
#940000
0*
#945000
b1010 "
b1010 9
b1010 T
b10 R
b1011101 5
1*
#950000
0*
#955000
17
b1011 "
b1011 9
b1011 T
b11 R
b1011110 5
1*
#960000
0*
#965000
07
b11000 D
b1100 "
b1100 9
b1100 T
b11000 S
b0 R
b1011111 5
1*
#970000
0*
#975000
b1101 "
b1101 9
b1101 T
b1 R
b1100000 5
1*
#980000
0*
#985000
b1110 "
b1110 9
b1110 T
b10 R
b1100001 5
1*
#990000
0*
#995000
17
b1111 "
b1111 9
b1111 T
b11 R
b1100010 5
1*
#1000000
0*
#1005000
07
b11001 D
b10000 "
b10000 9
b10000 T
b11001 S
b0 R
b1100011 5
1*
#1010000
0*
#1015000
b10001 "
b10001 9
b10001 T
b1 R
b1100100 5
1*
#1020000
0*
#1025000
b10010 "
b10010 9
b10010 T
b10 R
b1100101 5
1*
#1030000
0*
#1035000
17
b10011 "
b10011 9
b10011 T
b11 R
b1100110 5
1*
#1040000
0*
#1045000
07
b11010 D
b10100 "
b10100 9
b10100 T
b11010 S
b0 R
b1100111 5
1*
#1050000
0*
#1055000
b10101 "
b10101 9
b10101 T
b1 R
b1101000 5
1*
#1060000
0*
#1065000
b10110 "
b10110 9
b10110 T
b10 R
b1101001 5
1*
#1070000
0*
#1075000
17
b10111 "
b10111 9
b10111 T
b11 R
b1101010 5
1*
#1080000
0*
#1085000
07
b11011 D
b11000 "
b11000 9
b11000 T
b11011 S
b0 R
b1101011 5
1*
#1090000
0*
#1095000
b11001 "
b11001 9
b11001 T
b1 R
b1101100 5
1*
#1100000
0*
#1105000
b11010 "
b11010 9
b11010 T
b10 R
b1101101 5
1*
#1110000
0*
#1115000
17
b11011 "
b11011 9
b11011 T
b11 R
b1101110 5
1*
#1120000
0*
#1125000
b1 C
b1 V
07
b1 -
b1 8
b11100 D
b100 !
b100 :
b100 U
b0 "
b0 9
b0 T
b11100 S
b0 R
b1101111 5
1*
#1130000
0*
#1135000
b1 C
b0 -
b0 8
b1 V
b1 "
b1 9
b1 T
b1 R
b1 W
b1110000 5
1*
#1140000
0*
#1145000
b10 "
b10 9
b10 T
b10 R
b1110001 5
1*
#1150000
0*
#1155000
17
b11 "
b11 9
b11 T
b11 R
b1110010 5
1*
#1160000
0*
#1165000
07
b0 C
b11101 D
b0 V
b100 "
b100 9
b100 T
b11101 S
b0 R
b0 W
b1110011 5
1*
#1170000
0*
#1175000
b101 "
b101 9
b101 T
b1 R
b1110100 5
1*
#1180000
0*
#1185000
b110 "
b110 9
b110 T
b10 R
b1110101 5
1*
#1190000
0*
#1195000
17
b111 "
b111 9
b111 T
b11 R
b1110110 5
1*
#1200000
0*
#1205000
07
b11110 D
b1000 "
b1000 9
b1000 T
b11110 S
b0 R
b1110111 5
1*
#1210000
0*
#1215000
b1001 "
b1001 9
b1001 T
b1 R
b1111000 5
1*
#1220000
0*
#1225000
b1010 "
b1010 9
b1010 T
b10 R
b1111001 5
1*
#1230000
0*
#1235000
17
b1011 "
b1011 9
b1011 T
b11 R
b1111010 5
1*
#1240000
0*
#1245000
07
b11111 D
b1100 "
b1100 9
b1100 T
b11111 S
b0 R
b1111011 5
1*
#1250000
0*
#1255000
b1101 "
b1101 9
b1101 T
b1 R
b1111100 5
1*
#1260000
0*
#1265000
b1110 "
b1110 9
b1110 T
b10 R
b1111101 5
1*
#1270000
0*
#1275000
17
b1111 "
b1111 9
b1111 T
b11 R
b1111110 5
1*
#1280000
0*
#1285000
07
b100000 D
b10000 "
b10000 9
b10000 T
b100000 S
b0 R
b1111111 5
1*
#1290000
0*
#1295000
b10001 "
b10001 9
b10001 T
b1 R
b10000000 5
1*
#1300000
0*
#1305000
b10010 "
b10010 9
b10010 T
b10 R
b10000001 5
1*
#1310000
0*
#1315000
17
b10011 "
b10011 9
b10011 T
b11 R
b10000010 5
1*
#1320000
0*
#1325000
07
b100001 D
b10100 "
b10100 9
b10100 T
b100001 S
b0 R
b10000011 5
1*
#1330000
0*
#1335000
b10101 "
b10101 9
b10101 T
b1 R
b10000100 5
1*
#1340000
0*
#1345000
b10110 "
b10110 9
b10110 T
b10 R
b10000101 5
1*
#1350000
0*
#1355000
17
b10111 "
b10111 9
b10111 T
b11 R
b10000110 5
1*
#1360000
0*
#1365000
07
b100010 D
b11000 "
b11000 9
b11000 T
b100010 S
b0 R
b10000111 5
1*
#1370000
0*
#1375000
b11001 "
b11001 9
b11001 T
b1 R
b10001000 5
1*
#1380000
0*
#1385000
b11010 "
b11010 9
b11010 T
b10 R
b10001001 5
1*
#1390000
0*
#1395000
17
b11011 "
b11011 9
b11011 T
b11 R
b10001010 5
1*
#1400000
0*
#1405000
b1 C
b1 V
07
b1 -
b1 8
b100011 D
b101 !
b101 :
b101 U
b0 "
b0 9
b0 T
b100011 S
b0 R
b10001011 5
1*
#1410000
0*
#1415000
b1 C
b0 -
b0 8
b1 V
b1 "
b1 9
b1 T
b1 R
b1 W
b10001100 5
1*
#1420000
0*
#1425000
b10 "
b10 9
b10 T
b10 R
b10001101 5
1*
#1430000
0*
#1435000
17
b11 "
b11 9
b11 T
b11 R
b10001110 5
1*
#1440000
0*
#1445000
07
b0 C
b100100 D
b0 V
b100 "
b100 9
b100 T
b100100 S
b0 R
b0 W
b10001111 5
1*
#1450000
0*
#1455000
b1000 C
b1000 V
b10 -
b10 8
b101 "
b101 9
b101 T
b1 R
b10010000 5
1*
#1460000
0*
#1465000
b1000 C
b0 -
b0 8
b1000 V
b110 "
b110 9
b110 T
b10 R
b1000 W
b10010001 5
1*
#1470000
0*
#1475000
17
b111 "
b111 9
b111 T
b11 R
b10010010 5
1*
#1480000
0*
#1485000
07
b0 C
b100101 D
b0 V
b1000 "
b1000 9
b1000 T
b100101 S
b0 R
b0 W
b10010011 5
1*
#1490000
0*
