Pacman_FPGA/source/pacman_collision.sv
`default_nettype none

module pacman_collision (
    input  wire logic       clk,
    input  wire logic       reset,
    input  wire logic       game_tick,
    input  wire logic       game_running,
    input  wire logic       game_starting,

    input  wire logic [4:0] pacman_x,
    input  wire logic [4:0] pacman_y,

    input  wire logic [4:0] blinky_x,
    input  wire logic [4:0] blinky_y,
    input  wire logic [4:0] pinky_x,
    input  wire logic [4:0] pinky_y,

    input  wire logic [1:0] dangerous_to_pacman,
    input  wire logic [1:0] vulnerable_to_pacman,
    input  wire logic       power_pellet_active,

    // Maze lookup via arbiter (collision port)
    output logic [4:0]      col_x,
    output logic [4:0]      col_y,
    input  wire logic       col_valid,
    input  wire logic       col_collectible,
    input  wire logic       col_is_power,
    input  wire logic [7:0] col_pellet_index,

    // pellet_state interface
    input  wire logic       pellet_already_eaten,  // eaten bit at col_pellet_index
    output logic            pellet_set_en,
    output logic [7:0]      pellet_set_index,

    output logic            pellet_eaten,
    output logic            power_pellet_eaten,
    output logic            pacman_hit,
    output logic [1:0]      ghost_eaten,
    output logic [1:0]      lives,
    output logic [7:0]      pellets
);

    logic collide_blinky;
    logic collide_pinky;

    always_comb begin
        collide_blinky =
            (pacman_x == blinky_x) &&
            (pacman_y == blinky_y);

        collide_pinky =
            (pacman_x == pinky_x) &&
            (pacman_y == pinky_y);
    end

    // Always query Pac-Man's current tile.
    always_comb begin
        col_x = pacman_x;
        col_y = pacman_y;
    end

    always_ff @(posedge clk or posedge reset) begin
        if (reset) begin
            pellet_set_en      <= 1'b0;
            pellet_set_index   <= 8'd0;
            pellet_eaten       <= 1'b0;
            power_pellet_eaten <= 1'b0;
            pacman_hit         <= 1'b0;
            ghost_eaten        <= 2'b00;
            lives              <= 2'd3;
            pellets            <= 8'd186;
        end else if (game_starting) begin
            pellet_set_en      <= 1'b0;
            pellet_eaten       <= 1'b0;
            power_pellet_eaten <= 1'b0;
            pacman_hit         <= 1'b0;
            ghost_eaten        <= 2'b00;
            lives              <= 2'd3;
            pellets            <= 8'd186;
        end else begin
            pellet_set_en <= 1'b0;
            pellet_eaten  <= 1'b0;

            // Hold CDC events until the 60 Hz domain samples them, then clear.
            // Clear on the cycle after new_clock rises (game_tick still high).
            if (game_tick) begin
                power_pellet_eaten <= 1'b0;
                pacman_hit         <= 1'b0;
                ghost_eaten        <= 2'b00;
            end else if (game_running) begin
                if (collide_blinky) begin
                    if (power_pellet_active || vulnerable_to_pacman[0]) begin
                        if (!ghost_eaten[0])
                            ghost_eaten[0] <= 1'b1;
                    end else if (dangerous_to_pacman[0]) begin
                        if (!pacman_hit) begin
                            pacman_hit <= 1'b1;
                            lives <= lives - 2'd1;
                        end
                    end
                end

                if (collide_pinky) begin
                    if (power_pellet_active || vulnerable_to_pacman[1]) begin
                        if (!ghost_eaten[1])
                            ghost_eaten[1] <= 1'b1;
                    end else if (dangerous_to_pacman[1]) begin
                        if (!pacman_hit) begin
                            pacman_hit <= 1'b1;
                            lives <= lives - 2'd1;
                        end
                    end
                end

                // Pellet pickup: response must be valid for the current
                // position and the pellet must not already be eaten.
                if (col_valid && col_collectible && !pellet_already_eaten) begin
                    pellet_set_en    <= 1'b1;
                    pellet_set_index <= col_pellet_index;
                    pellets          <= pellets - 8'd1;

                    if (col_is_power) begin
                        power_pellet_eaten <= 1'b1;
                        pellet_eaten <= 1'b1;
                        
                    end else begin
                        pellet_eaten <= 1'b1;
                    end
                end
            end
        end
    end

endmodule

`default_nettype wire

Pacman_FPGA/testbench/pacman_collision_tb.sv
`timescale 1ns/1ps

module pacman_collision_tb;

    logic       clk;
    logic       reset;
    logic       game_tick;
    logic       game_running;
    logic       game_starting;

    logic [4:0] pacman_x, pacman_y;
    logic [4:0] blinky_x, blinky_y;
    logic [4:0] pinky_x, pinky_y;

    logic [1:0] dangerous_to_pacman;
    logic [1:0] vulnerable_to_pacman;
    logic       power_pellet_active;

    logic [4:0] col_x, col_y;
    logic       col_valid;
    logic       col_collectible;
    logic       col_is_power;
    logic [7:0] col_pellet_index;

    logic       pellet_already_eaten;
    logic       pellet_set_en;
    logic [7:0] pellet_set_index;

    logic       pellet_eaten;
    logic       power_pellet_eaten;
    logic       pacman_hit;
    logic [1:0] ghost_eaten;
    logic [1:0] lives;
    logic [7:0] pellets;

    int pass_count;
    int fail_count;
    int guard;

    // Simple eaten-bit model for the DUT's write/read handshake.
    logic [255:0] eaten_bits;

    always_ff @(posedge clk or posedge reset) begin
        if (reset || game_starting)
            eaten_bits <= '0;
        else if (pellet_set_en)
            eaten_bits[pellet_set_index] <= 1'b1;
    end

    always_comb begin
        pellet_already_eaten = eaten_bits[col_pellet_index];
        if (pellet_set_en && (pellet_set_index == col_pellet_index))
            pellet_already_eaten = 1'b1;
    end

    pacman_collision dut (
        .clk(clk),
        .reset(reset),
        .game_tick(game_tick),
        .game_running(game_running),
        .game_starting(game_starting),
        .pacman_x(pacman_x),
        .pacman_y(pacman_y),
        .blinky_x(blinky_x),
        .blinky_y(blinky_y),
        .pinky_x(pinky_x),
        .pinky_y(pinky_y),
        .dangerous_to_pacman(dangerous_to_pacman),
        .vulnerable_to_pacman(vulnerable_to_pacman),
        .power_pellet_active(power_pellet_active),
        .col_x(col_x),
        .col_y(col_y),
        .col_valid(col_valid),
        .col_collectible(col_collectible),
        .col_is_power(col_is_power),
        .col_pellet_index(col_pellet_index),
        .pellet_already_eaten(pellet_already_eaten),
        .pellet_set_en(pellet_set_en),
        .pellet_set_index(pellet_set_index),
        .pellet_eaten(pellet_eaten),
        .power_pellet_eaten(power_pellet_eaten),
        .pacman_hit(pacman_hit),
        .ghost_eaten(ghost_eaten),
        .lives(lives),
        .pellets(pellets)
    );

    initial clk = 1'b0;
    always #5 clk = ~clk;

    task automatic check(input string name, input logic cond);
        if (cond) begin
            pass_count++;
            $display("PASS: %s", name);
        end else begin
            fail_count++;
            $display("FAIL: %s (lives=%0d hit=%b ge=%b se=%b pe=%b ppe=%b pellets=%0d)",
                     name, lives, pacman_hit, ghost_eaten, pellet_set_en,
                     pellet_eaten, power_pellet_eaten, pellets);
        end
    endtask

    task automatic sample;
        @(posedge clk);
        #1;
    endtask

    task automatic wait_set_en;
        guard = 0;
        while ((pellet_set_en !== 1'b1) && (guard < 20)) begin
            sample();
            guard++;
        end
    endtask

    task automatic pulse_game_tick_and_sample;
        @(negedge clk);
        game_tick = 1'b1;
        @(posedge clk);
        #1;
    endtask

    task automatic release_game_tick;
        @(negedge clk);
        game_tick = 1'b0;
        sample();
    endtask

    task automatic clear_ghosts;
        blinky_x             = 5'd0;
        blinky_y             = 5'd0;
        pinky_x              = 5'd1;
        pinky_y              = 5'd1;
        dangerous_to_pacman  = 2'b00;
        vulnerable_to_pacman = 2'b00;
        power_pellet_active  = 1'b0;
    endtask

    initial begin
        pass_count            = 0;
        fail_count            = 0;
        reset                 = 1'b1;
        game_tick             = 1'b0;
        game_running          = 1'b0;
        game_starting         = 1'b0;
        pacman_x              = 5'd5;
        pacman_y              = 5'd5;
        clear_ghosts();
        col_valid             = 1'b0;
        col_collectible       = 1'b0;
        col_is_power          = 1'b0;
        col_pellet_index      = 8'd0;

        $dumpfile("waves/pacman_collision.vcd");
        $dumpvars(0, pacman_collision_tb);

        sample();
        sample();
        @(negedge clk);
        reset = 1'b0;
        sample();
        check("reset lives=3", lives === 2'd3);
        check("reset pellets=186", pellets === 8'd186);
        check("col addr tracks pacman", (col_x === pacman_x) && (col_y === pacman_y));

        col_valid       = 1'b1;
        col_collectible = 1'b1;
        col_is_power    = 1'b0;
        col_pellet_index = 8'd7;
        game_running    = 1'b0;
        repeat (4) sample();
        check("idle no set_en", pellet_set_en === 1'b0);
        check("idle pellets unchanged", pellets === 8'd186);

        @(negedge clk);
        game_running = 1'b1;
        wait_set_en();
        check("pellet set_en", pellet_set_en === 1'b1);
        check("pellet set_index", pellet_set_index === 8'd7);
        check("pellet_eaten pulse", pellet_eaten === 1'b1);
        check("pellets decremented", pellets === 8'd185);
        sample();
        check("pellet_eaten clears", pellet_eaten === 1'b0);
        check("already eaten blocks re-eat", pellet_set_en === 1'b0);

        @(negedge clk);
        col_pellet_index = 8'd8;
        col_is_power     = 1'b1;
        wait_set_en();
        check("power set_en", pellet_set_en === 1'b1);
        check("power_pellet_eaten set", power_pellet_eaten === 1'b1);
        check("pellets after power", pellets === 8'd184);

        @(negedge clk);
        col_collectible = 1'b0;
        col_is_power    = 1'b0;
        clear_ghosts();
        pulse_game_tick_and_sample();
        check("game_tick clears power flag", power_pellet_eaten === 1'b0);
        release_game_tick();

        @(negedge clk);
        blinky_x            = pacman_x;
        blinky_y            = pacman_y;
        dangerous_to_pacman = 2'b01;
        sample();
        check("dangerous blinky hits", pacman_hit === 1'b1);
        check("life lost", lives === 2'd2);
        sample();
        sample();
        check("hit held until game_tick", pacman_hit === 1'b1);

        @(negedge clk);
        clear_ghosts();
        pulse_game_tick_and_sample();
        check("game_tick clears hit", pacman_hit === 1'b0);
        release_game_tick();

        @(negedge clk);
        pinky_x              = pacman_x;
        pinky_y              = pacman_y;
        vulnerable_to_pacman = 2'b10;
        sample();
        check("pinky eaten flag", ghost_eaten === 2'b10);

        @(negedge clk);
        clear_ghosts();
        pulse_game_tick_and_sample();
        check("game_tick clears ghost_eaten", ghost_eaten === 2'b00);
        release_game_tick();

        @(negedge clk);
        blinky_x            = pacman_x;
        blinky_y            = pacman_y;
        power_pellet_active = 1'b1;
        sample();
        check("eat blinky under power", ghost_eaten[0] === 1'b1);

        @(negedge clk);
        clear_ghosts();
        game_starting = 1'b1;
        sample();
        check("game_starting restores pellets", pellets === 8'd186);
        check("game_starting restores lives", lives === 2'd3);
        game_starting = 1'b0;

        $display("\npacman_collision_tb: %0d PASS, %0d FAIL", pass_count, fail_count);
        if (fail_count != 0) $fatal(1);
        $finish;
    end

endmodule

Pacman_FPGA/waves/pacman_collision.vcd
$date
	Sat Aug  1 22:09:52 2026
$end
$version
	Icarus Verilog
$end
$timescale
	1ps
$end
$scope module pacman_collision_tb $end
$var wire 1 ! power_pellet_eaten $end
$var wire 8 " pellets [7:0] $end
$var wire 8 # pellet_set_index [7:0] $end
$var wire 1 $ pellet_set_en $end
$var wire 1 % pellet_eaten $end
$var wire 1 & pacman_hit $end
$var wire 2 ' lives [1:0] $end
$var wire 2 ( ghost_eaten [1:0] $end
$var wire 5 ) col_y [4:0] $end
$var wire 5 * col_x [4:0] $end
$var reg 5 + blinky_x [4:0] $end
$var reg 5 , blinky_y [4:0] $end
$var reg 1 - clk $end
$var reg 1 . col_collectible $end
$var reg 1 / col_is_power $end
$var reg 8 0 col_pellet_index [7:0] $end
$var reg 1 1 col_valid $end
$var reg 2 2 dangerous_to_pacman [1:0] $end
$var reg 256 3 eaten_bits [255:0] $end
$var reg 1 4 game_running $end
$var reg 1 5 game_starting $end
$var reg 1 6 game_tick $end
$var reg 5 7 pacman_x [4:0] $end
$var reg 5 8 pacman_y [4:0] $end
$var reg 1 9 pellet_already_eaten $end
$var reg 5 : pinky_x [4:0] $end
$var reg 5 ; pinky_y [4:0] $end
$var reg 1 < power_pellet_active $end
$var reg 1 = reset $end
$var reg 2 > vulnerable_to_pacman [1:0] $end
$var integer 32 ? fail_count [31:0] $end
$var integer 32 @ guard [31:0] $end
$var integer 32 A pass_count [31:0] $end
$scope module dut $end
$var wire 5 B blinky_x [4:0] $end
$var wire 5 C blinky_y [4:0] $end
$var wire 1 - clk $end
$var wire 1 . col_collectible $end
$var wire 1 / col_is_power $end
$var wire 8 D col_pellet_index [7:0] $end
$var wire 1 1 col_valid $end
$var wire 2 E dangerous_to_pacman [1:0] $end
$var wire 1 4 game_running $end
$var wire 1 5 game_starting $end
$var wire 1 6 game_tick $end
$var wire 5 F pacman_x [4:0] $end
$var wire 5 G pacman_y [4:0] $end
$var wire 1 9 pellet_already_eaten $end
$var wire 5 H pinky_x [4:0] $end
$var wire 5 I pinky_y [4:0] $end
$var wire 1 < power_pellet_active $end
$var wire 1 = reset $end
$var wire 2 J vulnerable_to_pacman [1:0] $end
$var reg 5 K col_x [4:0] $end
$var reg 5 L col_y [4:0] $end
$var reg 1 M collide_blinky $end
$var reg 1 N collide_pinky $end
$var reg 2 O ghost_eaten [1:0] $end
$var reg 2 P lives [1:0] $end
$var reg 1 & pacman_hit $end
$var reg 1 % pellet_eaten $end
$var reg 1 $ pellet_set_en $end
$var reg 8 Q pellet_set_index [7:0] $end
$var reg 8 R pellets [7:0] $end
$var reg 1 ! power_pellet_eaten $end
$upscope $end
$scope task check $end
$upscope $end
$scope task clear_ghosts $end
$upscope $end
$scope task pulse_game_tick_and_sample $end
$upscope $end
$scope task release_game_tick $end
$upscope $end
$scope task sample $end
$upscope $end
$scope task wait_set_en $end
$upscope $end
$upscope $end
$enddefinitions $end
$comment Show the parameter values. $end
$dumpall
$end
#0
$dumpvars
b10111010 R
b0 Q
b11 P
b0 O
0N
0M
b101 L
b101 K
b0 J
b1 I
b1 H
b101 G
b101 F
b0 E
b0 D
b0 C
b0 B
b0 A
b0 @
b0 ?
b0 >
1=
0<
b1 ;
b1 :
09
b101 8
b101 7
06
05
04
b0 3
b0 2
01
b0 0
0/
0.
0-
b0 ,
b0 +
b101 *
b101 )
b0 (
b11 '
0&
0%
0$
b0 #
b10111010 "
0!
$end
#5000
1-
#10000
0-
#15000
1-
#20000
0=
0-
#25000
1-
#26000
b111 0
b111 D
1.
11
b11 A
#30000
0-
#35000
1-
#40000
0-
#45000
1-
#50000
0-
#55000
1-
#60000
0-
#65000
1-
#66000
b101 A
#70000
14
0-
#75000
19
1%
b10111001 "
b10111001 R
b111 #
b111 Q
1$
1-
#76000
b1001 A
b1 @
#80000
0-
#85000
b10000000 3
0%
0$
1-
#86000
b1011 A
#90000
09
b0 @
1/
b1000 0
b1000 D
0-
#95000
19
1%
1!
b10111000 "
b10111000 R
b1000 #
b1000 Q
1$
1-
#96000
b1110 A
b1 @
#100000
0/
0.
0-
#105000
b110000000 3
0%
0$
1-
#110000
16
0-
#115000
0!
1-
#116000
b1111 A
#120000
06
0-
#125000
1-
#130000
1M
b1 2
b1 E
b101 ,
b101 C
b101 +
b101 B
0-
#135000
b10 '
b10 P
1&
1-
#136000
b10001 A
#140000
0-
#145000
1-
#150000
0-
#155000
1-
#156000
b10010 A
#160000
0M
b0 2
b0 E
b0 ,
b0 C
b0 +
b0 B
0-
#165000
1-
#170000
16
0-
#175000
0&
1-
#176000
b10011 A
#180000
06
0-
#185000
1-
#190000
1N
b10 >
b10 J
b101 ;
b101 I
b101 :
b101 H
0-
#195000
b10 (
b10 O
1-
#196000
b10100 A
#200000
0N
b0 >
b0 J
b1 ;
b1 I
b1 :
b1 H
0-
#205000
1-
#210000
16
0-
#215000
b0 (
b0 O
1-
#216000
b10101 A
#220000
06
0-
#225000
1-
#230000
1M
1<
b101 ,
b101 C
b101 +
b101 B
0-
#235000
b1 (
b1 O
1-
#236000
b10110 A
#240000
0M
15
0<
b0 ,
b0 C
b0 +
b0 B
0-
#245000
09
b0 3
b10111010 "
b10111010 R
b11 '
b11 P
b0 (
b0 O
1-
#246000
05
b11000 A
