Pacman_FPGA/source/pellet_state.sv
module pellet_state (
    input  logic       clk,
    input  logic       reset,

    input  logic       clear,        // synchronous clear-all (new game)

    input  logic       set_en,       // mark pellet as eaten
    input  logic [7:0] set_index,

    input  logic [7:0] rd_index_a,   // collision
    output logic       rd_bit_a,

    input  logic [7:0] rd_index_b,   // VGA
    output logic       rd_bit_b
);

    localparam int NUM_PELLETS = 186;

    logic [NUM_PELLETS-1:0] eaten;

    always_ff @(posedge clk or posedge reset) begin
        if (reset)
            eaten <= '0;
        else if (clear)
            eaten <= '0;
        else if (set_en && (set_index < 8'(NUM_PELLETS)))
            eaten[set_index] <= 1'b1;
    end

    always_comb begin
        rd_bit_a = (rd_index_a < 8'(NUM_PELLETS)) ? eaten[rd_index_a] : 1'b0;
        if (set_en && (set_index == rd_index_a))
            rd_bit_a = 1'b1;

        rd_bit_b = (rd_index_b < 8'(NUM_PELLETS)) ? eaten[rd_index_b] : 1'b0;
        if (set_en && (set_index == rd_index_b))
            rd_bit_b = 1'b1;
    end

endmodule

Pacman_FPGA/testbench/pellet_state_tb.sv
`timescale 1ns/1ps

module pellet_state_tb;

    logic       clk;
    logic       reset;
    logic       clear;
    logic       set_en;
    logic [7:0] set_index;
    logic [7:0] rd_index_a;
    logic       rd_bit_a;
    logic [7:0] rd_index_b;
    logic       rd_bit_b;

    int pass_count;
    int fail_count;

    pellet_state dut (
        .clk(clk),
        .reset(reset),
        .clear(clear),
        .set_en(set_en),
        .set_index(set_index),
        .rd_index_a(rd_index_a),
        .rd_bit_a(rd_bit_a),
        .rd_index_b(rd_index_b),
        .rd_bit_b(rd_bit_b)
    );

    initial clk = 1'b0;
    always #5 clk = ~clk;

    task automatic check(input string name, input logic cond);
        if (cond) begin
            pass_count++;
            $display("PASS: %s", name);
        end else begin
            fail_count++;
            $display("FAIL: %s (a=%b b=%b)", name, rd_bit_a, rd_bit_b);
        end
    endtask

    task automatic sample;
        @(posedge clk);
        #1;
    endtask

    initial begin
        pass_count = 0;
        fail_count = 0;
        reset      = 1'b1;
        clear      = 1'b0;
        set_en     = 1'b0;
        set_index  = 8'd0;
        rd_index_a = 8'd0;
        rd_index_b = 8'd1;

        $dumpfile("waves/pellet_state.vcd");
        $dumpvars(0, pellet_state_tb);

        sample();
        @(negedge clk);
        reset = 1'b0;
        sample();
        check("reset clears bits", (rd_bit_a === 1'b0) && (rd_bit_b === 1'b0));

        @(negedge clk);
        set_en     = 1'b1;
        set_index  = 8'd10;
        rd_index_a = 8'd10;
        sample();
        check("same-cycle bypass sets rd_a", rd_bit_a === 1'b1);
        @(negedge clk);
        set_en = 1'b0;
        sample();
        check("bit stays eaten", rd_bit_a === 1'b1);

        rd_index_b = 8'd10;
        #1;
        check("port b sees eaten", rd_bit_b === 1'b1);

        rd_index_a = 8'd11;
        #1;
        check("other index still clear", rd_bit_a === 1'b0);

        @(negedge clk);
        set_en    = 1'b1;
        set_index = 8'd200; // out of range
        sample();
        @(negedge clk);
        set_en = 1'b0;
        rd_index_a = 8'd200;
        #1;
        check("oob write ignored / read 0", rd_bit_a === 1'b0);

        @(negedge clk);
        clear = 1'b1;
        sample();
        rd_index_a = 8'd10;
        #1;
        check("clear restores uneaten", rd_bit_a === 1'b0);
        @(negedge clk);
        clear = 1'b0;

        $display("\npellet_state_tb: %0d PASS, %0d FAIL", pass_count, fail_count);
        if (fail_count != 0) $fatal(1);
        $finish;
    end

endmodule

Pacman_FPGA/waves/pellet_state.vcd
$date
	Sat Aug  1 22:09:52 2026
$end
$version
	Icarus Verilog
$end
$timescale
	1ps
$end
$scope module pellet_state_tb $end
$var wire 1 ! rd_bit_b $end
$var wire 1 " rd_bit_a $end
$var reg 1 # clear $end
$var reg 1 $ clk $end
$var reg 8 % rd_index_a [7:0] $end
$var reg 8 & rd_index_b [7:0] $end
$var reg 1 ' reset $end
$var reg 1 ( set_en $end
$var reg 8 ) set_index [7:0] $end
$var integer 32 * fail_count [31:0] $end
$var integer 32 + pass_count [31:0] $end
$scope module dut $end
$var wire 1 # clear $end
$var wire 1 $ clk $end
$var wire 8 , rd_index_a [7:0] $end
$var wire 8 - rd_index_b [7:0] $end
$var wire 1 ' reset $end
$var wire 1 ( set_en $end
$var wire 8 . set_index [7:0] $end
$var parameter 32 / NUM_PELLETS $end
$var reg 186 0 eaten [185:0] $end
$var reg 1 " rd_bit_a $end
$var reg 1 ! rd_bit_b $end
$upscope $end
$scope task check $end
$upscope $end
$scope task sample $end
$upscope $end
$upscope $end
$enddefinitions $end
$comment Show the parameter values. $end
$dumpall
b10111010 /
$end
#0
$dumpvars
b0 0
b0 .
b1 -
b0 ,
b0 +
b0 *
b0 )
0(
1'
b1 &
b0 %
0$
0#
0"
0!
$end
#5000
1$
#10000
0'
0$
#15000
1$
#16000
b1 +
#20000
1"
b1010 %
b1010 ,
b1010 )
b1010 .
1(
0$
#25000
b10000000000 0
1$
#26000
b10 +
#30000
0(
0$
#35000
1$
#36000
1!
b1010 &
b1010 -
b11 +
#37000
0"
b1011 %
b1011 ,
b100 +
#38000
b101 +
#40000
b11001000 )
b11001000 .
1(
0$
#45000
1$
#50000
b11001000 %
b11001000 ,
0(
0$
#51000
b110 +
#55000
1$
#60000
1#
0$
#65000
0!
b0 0
1$
#66000
b1010 %
b1010 ,
#67000
b111 +
#70000
0#
0$
