Pacman_FPGA/source/vga_draw_text.sv
module vga_draw_text(
    input  logic [9:0] h_count,    // Horizontal Display Counter
    input  logic [9:0] v_count,    // Vertical Display Counter
    input  logic       video_on, 
    input  logic [9:0] score,      //binary score from central control system
    input  logic [1:0] game_state,
    input  logic [2:0] input_rgb,  // pixel color from draw_tile
    output logic [2:0] output_rgb  // pixel color
);

    logic [4:0] tile_y;           // 0-27 Y tiles
    logic [4:0] tile_x;           // 0-35 X tiles
    logic [2:0] pixel_x, pixel_y; // 0-7 pixels in tile
    logic draw_pacman_text, draw_lose_text, draw_win_text, draw_press_button_text; // whether to draw the text or not
    logic draw_s, draw_c, draw_o, draw_r, draw_e;
 
  // digit tile enables (to the right of "SCORE")
    logic draw_hundreds, draw_tens, draw_ones;

    // decimal digits of the binary score
    logic [3:0] hundreds, tens, ones;
    logic [3:0] cur_digit;   // which digit this tile shows
    logic [7:0] cur_row;     // that digit's glyph row
    logic       cur_pix;     // the single pixel we want

    localparam [113:0] ROW2 = 114'h39cf39c32511c97df3247cc1c8322;
    localparam [113:0] ROW3 = 114'h25284204b511291044b41121284a2;
    localparam [113:0] ROW4 = 114'h39ce3987ace1c91044ac1121c879c;
    localparam [113:0] ROW5 = 114'h21480844a441291044a4112108488;
    localparam [113:0] ROW6 = 114'h212f7384a441c610432410c10f488;

    logic pixel_on; // whether to draw the text pixel or not
    logic [9:0] text_x;

    // Glyph row lookup for score digits (must be declared before use)
    function automatic logic [7:0] digit_row(input logic [3:0] digit, input logic [2:0] row);
        case (digit)
          4'd0: case (row)
            3'd0: digit_row = 8'b00111100;
            3'd1: digit_row = 8'b01100110;
            3'd2: digit_row = 8'b01100110;
            3'd3: digit_row = 8'b01100110;
            3'd4: digit_row = 8'b01100110;
            3'd5: digit_row = 8'b01100110;
            3'd6: digit_row = 8'b00111100;
            3'd7: digit_row = 8'b00000000;
          endcase
          4'd1: case (row)
            3'd0: digit_row = 8'b00011000;
            3'd1: digit_row = 8'b00111000;
            3'd2: digit_row = 8'b00011000;
            3'd3: digit_row = 8'b00011000;
            3'd4: digit_row = 8'b00011000;
            3'd5: digit_row = 8'b00011000;
            3'd6: digit_row = 8'b01111110;
            3'd7: digit_row = 8'b00000000;
          endcase
          4'd2: case (row)
            3'd0: digit_row = 8'b00111100;
            3'd1: digit_row = 8'b01100110;
            3'd2: digit_row = 8'b00000110;
            3'd3: digit_row = 8'b00001100;
            3'd4: digit_row = 8'b00110000;
            3'd5: digit_row = 8'b01100000;
            3'd6: digit_row = 8'b01111110;
            3'd7: digit_row = 8'b00000000;
          endcase
          4'd3: case (row)
            3'd0: digit_row = 8'b00111100;
            3'd1: digit_row = 8'b01100110;
            3'd2: digit_row = 8'b00000110;
            3'd3: digit_row = 8'b00011100;
            3'd4: digit_row = 8'b00000110;
            3'd5: digit_row = 8'b01100110;
            3'd6: digit_row = 8'b00111100;
            3'd7: digit_row = 8'b00000000;
          endcase
          4'd4: case (row)
            3'd0: digit_row = 8'b00001100;
            3'd1: digit_row = 8'b00011100;
            3'd2: digit_row = 8'b00111100;
            3'd3: digit_row = 8'b01101100;
            3'd4: digit_row = 8'b01111110;
            3'd5: digit_row = 8'b00001100;
            3'd6: digit_row = 8'b00001100;
            3'd7: digit_row = 8'b00000000;
          endcase
          4'd5: case (row)
            3'd0: digit_row = 8'b01111110;
            3'd1: digit_row = 8'b01100000;
            3'd2: digit_row = 8'b01111100;
            3'd3: digit_row = 8'b00000110;
            3'd4: digit_row = 8'b00000110;
            3'd5: digit_row = 8'b01100110;
            3'd6: digit_row = 8'b00111100;
            3'd7: digit_row = 8'b00000000;
          endcase
          4'd6: case (row)
            3'd0: digit_row = 8'b00111100;
            3'd1: digit_row = 8'b01100000;
            3'd2: digit_row = 8'b01100000;
            3'd3: digit_row = 8'b01111100;
            3'd4: digit_row = 8'b01100110;
            3'd5: digit_row = 8'b01100110;
            3'd6: digit_row = 8'b00111100;
            3'd7: digit_row = 8'b00000000;
          endcase
          4'd7: case (row)
            3'd0: digit_row = 8'b01111110;
            3'd1: digit_row = 8'b00000110;
            3'd2: digit_row = 8'b00001100;
            3'd3: digit_row = 8'b00011000;
            3'd4: digit_row = 8'b00110000;
            3'd5: digit_row = 8'b00110000;
            3'd6: digit_row = 8'b00110000;
            3'd7: digit_row = 8'b00000000;
          endcase
          4'd8: case (row)
            3'd0: digit_row = 8'b00111100;
            3'd1: digit_row = 8'b01100110;
            3'd2: digit_row = 8'b01100110;
            3'd3: digit_row = 8'b00111100;
            3'd4: digit_row = 8'b01100110;
            3'd5: digit_row = 8'b01100110;
            3'd6: digit_row = 8'b00111100;
            3'd7: digit_row = 8'b00000000;
          endcase
          4'd9: case (row)
            3'd0: digit_row = 8'b00111100;
            3'd1: digit_row = 8'b01100110;
            3'd2: digit_row = 8'b01100110;
            3'd3: digit_row = 8'b00111110;
            3'd4: digit_row = 8'b00000110;
            3'd5: digit_row = 8'b00000110;
            3'd6: digit_row = 8'b00111100;
            3'd7: digit_row = 8'b00000000;
          endcase
          default: digit_row = 8'b00000000;
        endcase
    endfunction

    // Determine tile location and pixel position
    assign tile_y = v_count[7:3];
    assign tile_x = h_count[7:3];
    assign pixel_y = v_count[2:0];
    assign pixel_x = h_count[2:0];

    assign draw_pacman_text =
        (tile_y >= 5'd18) && (tile_y <= 5'd21) &&
        (tile_x >= 5'd1)  && (tile_x < 5'd27);

    assign draw_lose_text =
        (tile_y >= 5'd18) && (tile_y <= 5'd21) &&
        (tile_x >= 5'd3)  && (tile_x < 5'd25);

    assign draw_win_text =
        (tile_y >= 5'd18) && (tile_y <= 5'd21) &&
        (tile_x >= 5'd4)  && (tile_x < 5'd25);

    assign draw_press_button_text =
        (tile_y == 5'd24) &&
        (tile_x >= 5'd7)  && (tile_x < 5'd21);

    assign draw_s = (h_count <= 7) && (h_count > 0) && (v_count < 8);
    assign draw_c = (h_count <= 15) && (h_count > 7) && (v_count < 8);
    assign draw_o = (h_count <= 23) && (h_count > 15) && (v_count < 8);
    assign draw_r = (h_count <= 31) && (h_count > 23) && (v_count < 8);
    assign draw_e = (h_count <= 39) && (h_count > 31) && (v_count < 8);

    // tile 5 is a blank gap.
    // tile 6 = hundreds, tile 7 = tens, tile 8 = ones.
    assign draw_hundreds = (h_count >= 48) && (h_count < 56) && (v_count < 8);
    assign draw_tens     = (h_count >= 56) && (h_count < 64) && (v_count < 8);
    assign draw_ones     = (h_count >= 64) && (h_count < 72) && (v_count < 8);

    // binary score -> decimal digits
    assign hundreds = 4'((score / 10'd100) % 10'd10);
    assign tens     = 4'((score / 10'd10)  % 10'd10);
    assign ones     = 4'( score            % 10'd10);

    always_comb begin
        if (draw_tens)
            cur_digit = tens;
        else if (draw_ones)
            cur_digit = ones;
        else
            cur_digit = hundreds;
    end

    assign cur_row = digit_row(cur_digit, pixel_y);
    assign cur_pix = cur_row[3'd7 - pixel_x];

    always_comb begin
        pixel_on = 1'b0;
        text_x = h_count - 10'd56;   // tile 7 = 7*8 = 56

        if (draw_press_button_text && text_x < 114) begin
            case (pixel_y)
                3'd2: pixel_on = ROW2[113-text_x];
                3'd3: pixel_on = ROW3[113-text_x];
                3'd4: pixel_on = ROW4[113-text_x];
                3'd5: pixel_on = ROW5[113-text_x];
                3'd6: pixel_on = ROW6[113-text_x];
                default: pixel_on = 1'b0;
            endcase
        end
    end





    always_comb begin
        // Default: pass through background
        output_rgb = input_rgb;
        //draw press any button to play text

        if (game_state == 2'b00 && draw_pacman_text && video_on) begin
            case (tile_y)

                // P  A  C  M  A  N
                5'd18:
                    output_rgb =
                        (tile_x != 4  &&
                         tile_x != 8  &&
                         tile_x != 12 &&
                         tile_x != 18 &&
                         tile_x != 22 &&
                         tile_x != 24 &&
                         tile_x != 25)
                        ? 3'b111 : input_rgb;

                5'd19:
                    output_rgb =
                        (tile_x != 2  &&
                         tile_x != 4  &&
                         tile_x != 6  &&
                         tile_x != 8  &&
                         tile_x != 10 &&
                         tile_x != 11 &&
                         tile_x != 12 &&
                         tile_x != 14 &&
                         tile_x != 16 &&
                         tile_x != 18 &&
                         tile_x != 20 &&
                         tile_x != 22 &&
                         tile_x != 25)
                        ? 3'b111 : input_rgb;

                5'd20:
                    output_rgb =
                        (tile_x != 4  &&
                         tile_x != 8  &&
                         tile_x != 10 &&
                         tile_x != 11 &&
                         tile_x != 12 &&
                         tile_x != 14 &&
                         tile_x != 16 &&
                         tile_x != 18 &&
                         tile_x != 22 &&
                         tile_x != 24)
                        ? 3'b111 : input_rgb;

                5'd21:
                    output_rgb =
                        (tile_x != 2  &&
                         tile_x != 3  &&
                         tile_x != 4  &&
                         tile_x != 6  &&
                         tile_x != 8  &&
                         tile_x != 12 &&
                         tile_x != 14 &&
                         tile_x != 16 &&
                         tile_x != 18 &&
                         tile_x != 20 &&
                         tile_x != 22 &&
                         tile_x != 24 &&
                         tile_x != 25)
                        ? 3'b111 : input_rgb;

                default: ;
            endcase
        end else if (game_state == 2'b10 && draw_lose_text && video_on) begin
            case (tile_y)

                // U SUCK!
                5'd18:
                      output_rgb =
                          (tile_x != 4  &&
                          tile_x != 6  &&
                          tile_x != 7 &&
                          tile_x != 9 &&
                          tile_x != 10 &&
                          tile_x != 11 &&
                          tile_x != 15 &&
                          tile_x != 19 &&
                          tile_x != 23)
                          ? 3'b111 : input_rgb;

                5'd19:
                      output_rgb =
                          (tile_x != 4  &&
                          tile_x != 6  &&
                          tile_x != 7  &&
                          tile_x != 9 &&
                          tile_x != 10 &&
                          tile_x != 11 &&
                          tile_x != 13 &&
                          tile_x != 15 && 
                          tile_x != 17 && //.5
                          tile_x != 18 && //.5
                          tile_x != 19 &&
                          tile_x != 21 && //.5
                          tile_x != 22 && //.5
                          tile_x != 23)   
                          ? 3'b111 : ((tile_x == 17 || tile_x == 18 || tile_x == 21 || tile_x == 22) && pixel_y >= 3'd5) ? 3'b111 : input_rgb;

                5'd20:
                      output_rgb =
                          (tile_x != 4  &&
                          tile_x != 6  &&
                          tile_x != 7  &&
                          tile_x != 9 &&
                          tile_x != 10 &&
                          tile_x != 11 &&
                          tile_x != 13 &&
                          tile_x != 15 && 
                          tile_x != 16 && //.5
                          tile_x != 17 && //.5
                          tile_x != 19 &&
                          tile_x != 21 && //.5
                          tile_x != 22 && //.5
                          tile_x != 23 &&
                          tile_x != 24) //.5   
                          ? 3'b111 : ((tile_x == 16 || tile_x == 17 || tile_x == 21 || tile_x == 22 || tile_x == 24) && pixel_y <= 3'd3) ? 3'b111 : input_rgb;

                5'd21:
                    output_rgb =
                        (tile_x != 6  &&
                         tile_x != 7  &&
                         tile_x != 11  &&
                         tile_x != 15  &&
                         tile_x != 19  &&
                         tile_x != 23
                        )
                        ? 3'b111 : input_rgb;

                default: ;
            endcase

        end else if (game_state == 2'b11 && draw_win_text && video_on) begin
            case (tile_y)

                // U WIN!
                5'd18:
                      output_rgb =
                          (tile_x != 5  &&
                          tile_x != 7  &&
                          tile_x != 8 &&
                          tile_x != 10 &&
                          tile_x != 11 &&
                          tile_x != 12 &&
                          tile_x != 14 &&
                          tile_x != 18 &&
                          tile_x != 20 &&
                          tile_x != 21 &&
                          tile_x != 23)
                          ? 3'b111 : input_rgb;

                5'd19:
                      output_rgb =
                          (tile_x != 5  &&
                          tile_x != 7  &&
                          tile_x != 8 &&
                          tile_x != 10 &&
                          tile_x != 12 &&
                          tile_x != 14 &&
                          tile_x != 15 &&
                          tile_x != 17 &&
                          tile_x != 18 &&
                          tile_x != 21 &&
                          tile_x != 23)
                          ? 3'b111 : input_rgb;

                5'd20:
                      output_rgb =
                          (tile_x != 5  &&
                          tile_x != 7  &&
                          tile_x != 8 &&
                          tile_x != 10 &&
                          tile_x != 12 &&
                          tile_x != 14 &&
                          tile_x != 15 &&
                          tile_x != 17 &&
                          tile_x != 18 &&
                          tile_x != 20 &&
                          tile_x != 23 &&
                          tile_x != 24)
                          ? 3'b111 : (tile_x == 24 && pixel_y <= 3'd3) ? 3'b111 : input_rgb;

                5'd21:
                      output_rgb =
                          (
                          tile_x != 7  &&
                          tile_x != 8 &&
                          tile_x != 9 &&
                          tile_x != 11 &&
                          tile_x != 13 &&
                          tile_x != 14 &&
                          tile_x != 18 &&
                          tile_x != 20 &&
                          tile_x != 21 &&
                          tile_x != 23)
                          ? 3'b111 : input_rgb;

                default: ;
            endcase
        
        end else if (game_state != 2'b01 && draw_press_button_text && video_on) begin

          output_rgb = pixel_on ? 3'b111 : input_rgb;

        end else if (draw_s && video_on)begin
          casez (pixel_y)
              3'd0 : output_rgb  =  3'b111;
              3'd1 : output_rgb =   3'b111;
              3'd2 : output_rgb = (pixel_x < 3)?  3'b111 : 3'b000;
              3'd3 : output_rgb =   3'b111;
              3'd4 : output_rgb =   3'b111;
              3'd5 : output_rgb =  (pixel_x > 5)?  3'b111 : 3'b000;
              3'd6 : output_rgb =  3'b111;
              3'd7 : output_rgb =  3'b111;     
          endcase
      
        end else if (draw_c && video_on)begin
          casez (pixel_y)
            3'd0 : output_rgb = (pixel_x != 0 && pixel_x <  7)?        3'b111 : 3'b000;
            3'd1 : output_rgb = (pixel_x != 0 && pixel_x <  7)?        3'b111 : 3'b000;
            3'd2 : output_rgb = (pixel_x ==1  || pixel_x == 2)?        3'b111 : 3'b000;
            3'd3 : output_rgb = (pixel_x ==1  || pixel_x == 2)?        3'b111 : 3'b000;
            3'd4 : output_rgb = (pixel_x ==1  || pixel_x == 2)?        3'b111 : 3'b000;
            3'd5 : output_rgb = (pixel_x ==1  || pixel_x == 2)?        3'b111 : 3'b000;
            3'd6 : output_rgb = (pixel_x != 0 && pixel_x <  7)?        3'b111 : 3'b000;
            3'd7 : output_rgb = (pixel_x != 0 && pixel_x <  7)?        3'b111 : 3'b000;    
          endcase
      
        end else if (draw_o && video_on)begin
          casez (pixel_y)
            3'd0 : output_rgb  =  3'b111;
            3'd1 : output_rgb  =  3'b111;
            3'd2 : output_rgb = (pixel_x < 2 || pixel_x > 6)?          3'b111 : 3'b000;
            3'd3 : output_rgb = (pixel_x < 2 || pixel_x > 6)?          3'b111 : 3'b000;
            3'd4 : output_rgb = (pixel_x < 2 || pixel_x > 6)?          3'b111 : 3'b000;
            3'd5 : output_rgb = (pixel_x < 2 || pixel_x > 6)?          3'b111 : 3'b000;
            3'd6 : output_rgb  =  3'b111;
            3'd7 : output_rgb  =  3'b111; 
          endcase
  
  
        end else if (draw_r && video_on)begin
          casez (pixel_y)
            3'd0 : output_rgb = (pixel_x > 0)?                                                   3'b111 : 3'b000;
            3'd1 : output_rgb = (pixel_x != 0 && pixel_x != 3 && pixel_x !=4 && pixel_x != 5)?   3'b111 : 3'b000;
            3'd2 : output_rgb = (pixel_x != 0 && pixel_x != 3 && pixel_x !=4 && pixel_x != 5)?   3'b111 : 3'b000;
            3'd3 : output_rgb = (pixel_x > 0)?                                                   3'b111 : 3'b000;
            3'd4 : output_rgb = (pixel_x > 0 || pixel_x < 6)?                                    3'b111 : 3'b000;
            3'd5 : output_rgb = ((pixel_x > 0 && pixel_x < 3)|| (pixel_x > 3 && pixel_x < 7))?   3'b111 : 3'b000;
            3'd6 : output_rgb = ((pixel_x > 0 && pixel_x < 3)|| pixel_x > 4)?                    3'b111 : 3'b000;
            3'd7 : output_rgb = ((pixel_x > 0 && pixel_x < 3)|| pixel_x > 5)?                    3'b111 : 3'b000;    
          endcase
  
  
        end else if (draw_e && video_on)begin
          casez (pixel_y)
            3'd0 : output_rgb = (pixel_x> 1 && pixel_x < 7)?           3'b111 : 3'b000;
            3'd1 : output_rgb = (pixel_x> 1 && pixel_x < 7)?           3'b111 : 3'b000;
            3'd2 : output_rgb = (pixel_x == 3 || pixel_x == 2)?        3'b111 : 3'b000;
            3'd3 : output_rgb = (pixel_x> 1 && pixel_x < 7)?           3'b111 : 3'b000;
            3'd4 : output_rgb = (pixel_x> 1 && pixel_x < 7)?           3'b111 : 3'b000;
            3'd5 : output_rgb = (pixel_x == 3 || pixel_x == 2)?        3'b111 : 3'b000;
            3'd6 : output_rgb = (pixel_x> 1 && pixel_x < 7)?           3'b111 : 3'b000;
            3'd7 : output_rgb = (pixel_x> 1 && pixel_x < 7)?           3'b111 : 3'b000;    
          endcase
 




    // draw numbers
    // basically a function gives you the values of the pixels in a row based on the height of the pixel y and then
    // access the value of the pixel you access it through array indexing and the leftmost is 7

       end else if ((draw_hundreds || draw_tens || draw_ones) && video_on) begin

            output_rgb = cur_pix ? 3'b111 : 3'b000;

       end else

        output_rgb = input_rgb;


    end

endmodule

Pacman_FPGA/testbench/vga_draw_text_tb.sv
`timescale 1ns/1ps

module vga_draw_text_tb;

    logic [9:0] h_count, v_count;
    logic       video_on;
    logic [9:0] score;
    logic [1:0] game_state;
    logic [2:0] input_rgb;
    logic [2:0] output_rgb;

    int pass_count;
    int fail_count;

    localparam logic [1:0] GAME_STARTING = 2'd0;
    localparam logic [1:0] GAME_PLAYING  = 2'd1;
    localparam logic [1:0] GAME_OVER     = 2'd2;
    localparam logic [1:0] GAME_WIN      = 2'd3;

    vga_draw_text dut (
        .h_count(h_count),
        .v_count(v_count),
        .video_on(video_on),
        .score(score),
        .game_state(game_state),
        .input_rgb(input_rgb),
        .output_rgb(output_rgb)
    );

    task automatic check(input string name, input logic cond);
        if (cond) begin
            pass_count++;
            $display("PASS: %s", name);
        end else begin
            fail_count++;
            $display("FAIL: %s (rgb=%b)", name, output_rgb);
        end
    endtask

    initial begin
        pass_count = 0;
        fail_count = 0;
        video_on   = 1'b1;
        score      = 10'd0;
        game_state = GAME_PLAYING;
        input_rgb  = 3'b001;
        h_count    = 10'd100;
        v_count    = 10'd100;

        $dumpfile("waves/vga_draw_text.vcd");
        $dumpvars(0, vga_draw_text_tb);

        #1;
        check("playing mid-screen pass-through", output_rgb === 3'b001);

        // SCORE 'S' glyph region: h in (0,7], v < 8 — solid white on rows 0/1
        h_count = 10'd4;
        v_count = 10'd0;
        #1;
        check("SCORE S glyph white", output_rgb === 3'b111);

        // Digit ones place for score=7 -> ones=7: h in [64,72), v<8
        // Digit 7 row0 = 8'b00111100, pixel_x=0 -> bit7=0 -> black
        score   = 10'd7;
        h_count = 10'd64; // pixel_x = 0
        v_count = 10'd0;
        #1;
        check("digit 7 leading black", output_rgb === 3'b000);

        h_count = 10'd66; // pixel_x = 2, bit5 of 00111100 = 1
        #1;
        check("digit 7 body white", output_rgb === 3'b111);

        // Hundreds for score=123: hundreds=1
        score   = 10'd123;
        h_count = 10'd51; // hundreds tile start 48, pixel_x=3
        v_count = 10'd6;  // digit 1 row6 = 01111110, pix3 = 1
        #1;
        check("hundreds digit drawn", output_rgb === 3'b111);

        // Title screen PAC-MAN banner: tile_y 18-21, lit tiles white
        game_state = GAME_STARTING;
        // tile_y = v[7:3] = 18 => v in [144,151]; tile_x=1 => h in [8,15]
        h_count = 10'd8;
        v_count = 10'd144;
        #1;
        check("starting title white block", output_rgb === 3'b111);

        // Game over text region
        game_state = GAME_OVER;
        h_count    = 10'd24; // tile_x = 3
        v_count    = 10'd144;
        #1;
        check("game over text white", output_rgb === 3'b111);

        // Win text
        game_state = GAME_WIN;
        h_count    = 10'd32; // tile_x = 4
        v_count    = 10'd144;
        #1;
        check("win text white", output_rgb === 3'b111);

        video_on = 1'b0;
        #1;
        check("video_off pass-through", output_rgb === 3'b001);

        $display("\nvga_draw_text_tb: %0d PASS, %0d FAIL", pass_count, fail_count);
        $finish;
    end

endmodule

Pacman_FPGA/waves/vga_draw_text.vcd
$date
	Sat Aug  1 00:16:17 2026
$end
$version
	Icarus Verilog
$end
$timescale
	1ps
$end
$scope module vga_draw_text_tb $end
$var wire 3 ! output_rgb [2:0] $end
$var parameter 2 " GAME_OVER $end
$var parameter 2 # GAME_PLAYING $end
$var parameter 2 $ GAME_STARTING $end
$var parameter 2 % GAME_WIN $end
$var reg 2 & game_state [1:0] $end
$var reg 10 ' h_count [9:0] $end
$var reg 3 ( input_rgb [2:0] $end
$var reg 10 ) score [9:0] $end
$var reg 10 * v_count [9:0] $end
$var reg 1 + video_on $end
$var integer 32 , fail_count [31:0] $end
$var integer 32 - pass_count [31:0] $end
$scope module dut $end
$var wire 1 . draw_c $end
$var wire 1 / draw_e $end
$var wire 1 0 draw_hundreds $end
$var wire 1 1 draw_lose_text $end
$var wire 1 2 draw_o $end
$var wire 1 3 draw_ones $end
$var wire 1 4 draw_pacman_text $end
$var wire 1 5 draw_press_button_text $end
$var wire 1 6 draw_r $end
$var wire 1 7 draw_s $end
$var wire 1 8 draw_tens $end
$var wire 1 9 draw_win_text $end
$var wire 2 : game_state [1:0] $end
$var wire 10 ; h_count [9:0] $end
$var wire 3 < input_rgb [2:0] $end
$var wire 10 = score [9:0] $end
$var wire 10 > v_count [9:0] $end
$var wire 1 + video_on $end
$var wire 5 ? tile_y [4:0] $end
$var wire 5 @ tile_x [4:0] $end
$var wire 4 A tens [3:0] $end
$var wire 3 B pixel_y [2:0] $end
$var wire 3 C pixel_x [2:0] $end
$var wire 4 D ones [3:0] $end
$var wire 4 E hundreds [3:0] $end
$var wire 8 F cur_row [7:0] $end
$var wire 1 G cur_pix $end
$var parameter 114 H ROW2 $end
$var parameter 114 I ROW3 $end
$var parameter 114 J ROW4 $end
$var parameter 114 K ROW5 $end
$var parameter 114 L ROW6 $end
$var reg 4 M cur_digit [3:0] $end
$var reg 3 N output_rgb [2:0] $end
$var reg 1 O pixel_on $end
$var reg 10 P text_x [9:0] $end
$scope function digit_row $end
$upscope $end
$upscope $end
$scope task check $end
$upscope $end
$upscope $end
$enddefinitions $end
$comment Show the parameter values. $end
$dumpall
b100001001011110111001110000100101001000100000111000110000100000100001100100100000100001100000100001111010010001000 L
b100001010010000000100001000100101001000100000100101001000100000100010010100100000100010010000100001000010010001000 K
b111001110011100011100110000111101011001110000111001001000100000100010010101100000100010010000111001000011110011100 J
b100101001010000100001000000100101101010001000100101001000100000100010010110100000100010010000100101000010010100010 I
b111001110011110011100111000011001001010001000111001001011111011111001100100100011111001100000111001000001100100010 H
b11 %
b0 $
b1 #
b10 "
$end
#0
$dumpvars
b101100 P
0O
b1 N
b0 M
0G
b1100110 F
b0 E
b0 D
b100 C
b100 B
b0 A
b1100 @
b1100 ?
b1100100 >
b0 =
b1 <
b1100100 ;
b1 :
09
08
07
06
05
04
03
02
01
00
0/
0.
b0 -
b0 ,
1+
b1100100 *
b0 )
b1 (
b1100100 '
b1 &
b1 !
$end
#1000
1G
b111100 F
b111 !
b111 N
b0 ?
b0 B
17
b1111001100 P
b0 @
b0 *
b0 >
b100 '
b100 ;
b1 -
#2000
b1111110 F
b111 M
b0 !
b0 N
07
13
b1000 P
b1000 @
0G
b0 C
b111 D
b1000000 '
b1000000 ;
b111 )
b111 =
b10 -
#3000
b111 !
b111 N
b1010 P
1G
b10 C
b1000010 '
b1000010 ;
b11 -
#4000
b1111110 F
b111 !
b111 N
10
03
b1 M
b110 B
b1111111011 P
b110 @
b11 C
b1 E
b10 A
b11 D
b110 *
b110 >
b110011 '
b110011 ;
b1111011 )
b1111011 =
b100 -
#5000
14
b11000 F
b10010 ?
b0 B
00
b1111010000 P
b1 @
0G
b0 C
b111 !
b111 N
b10010000 *
b10010000 >
b1000 '
b1000 ;
b0 &
b0 :
b101 -
#6000
11
b1111100000 P
b11 @
b111 !
b111 N
b11000 '
b11000 ;
b10 &
b10 :
b110 -
#7000
19
b1111101000 P
b100 @
b111 !
b111 N
b100000 '
b100000 ;
b11 &
b11 :
b111 -
#8000
b1 !
b1 N
0+
b1000 -
#9000
b1001 -
