Pacman_FPGA/source/vga_draw_tile.sv
module vga_draw_tile(
  input  logic       map_loaded,

  // requests tile to RAM
  input  logic [9:0] h_count_raw,
  input  logic [9:0] v_count_raw,
  input logic        video_on_raw,

  // draw delayed tile given from RAM
  input  logic [9:0] h_count_d,
  input  logic [9:0] v_count_d,
  input  logic       video_on_d,

  // RAM VGA port
  output logic [4:0] x_vga,
  output logic [4:0] y_vga,
  input  logic [1:0] tile_data,
  output logic [2:0] output_rgb
);
  logic in_map_raw;
  logic in_map_d;

  //variables
  logic black_right, black_bottom, black_top;
  logic [4:0] tile_x_raw, tile_y_raw;
  logic [2:0] pixel_x_d, pixel_y_d;
  
  //determine tile location and pixel position in tile
  assign tile_x_raw = h_count_raw[7:3];
  assign tile_y_raw = v_count_raw[7:3] + 5'd24;
  assign pixel_y_d = v_count_d[2:0]; //remainder
  assign pixel_x_d = h_count_d[2:0];

  assign in_map_raw = video_on_raw && (tile_x_raw < 5'd28) && (tile_y_raw < 5'd31);

  always_comb begin
    if (in_map_raw) begin
      x_vga = tile_x_raw;
      y_vga = tile_y_raw;
    end else begin
      x_vga = 5'd0;
      y_vga = 5'd0;
    end
  end

  assign in_map_d = video_on_d && ((h_count_d[7:3]) < 5'd28) && ((v_count_d[7:3] + 5'd24) < 5'd31);
  
  //pixel generator for tile
  always_comb begin
    output_rgb = 3'b000;
    if (!video_on_d || !map_loaded || !in_map_d) begin
      output_rgb = 3'b000;
    end else begin
      case (tile_data)
        2'b0: begin 
          output_rgb = 3'b000;
        end
        2'b01: begin
          output_rgb = 3'b001;
        end
        2'b10: begin
          if ((pixel_x_d == 3'd3 || pixel_x_d == 3'd4) && (pixel_y_d == 3'd3 || pixel_y_d == 3'd4)) begin
            output_rgb = 3'b111;
          end else begin
            output_rgb = 3'b000;
          end
        end
        2'b11: begin
          if ((pixel_x_d > 3'd0) && (pixel_x_d < 3'd7) && (pixel_y_d > 3'd0) && (pixel_y_d < 3'd7)) begin
            if ((pixel_x_d == 3'd1 || pixel_x_d == 3'd6) && (pixel_y_d == 3'd1 || pixel_y_d == 3'd6)) begin
              output_rgb = 3'b000;
            end else begin
              output_rgb = 3'b111;
            end
          end else begin
            output_rgb = 3'b000;
          end
        end
        default: begin
          output_rgb = 3'b000;
        end
      endcase
    end
  end
endmodule

Pacman_FPGA/testbench/vga_draw_tile_tb.sv
`timescale 1ns/1ps

module vga_draw_tile_tb;

    logic       map_loaded;
    logic [9:0] h_count_raw, v_count_raw;
    logic       video_on_raw;
    logic [9:0] h_count_d, v_count_d;
    logic       video_on_d;
    logic [4:0] x_vga, y_vga;
    logic [1:0] tile_data;
    logic [2:0] output_rgb;

    int pass_count;
    int fail_count;

    vga_draw_tile dut (
        .map_loaded(map_loaded),
        .h_count_raw(h_count_raw),
        .v_count_raw(v_count_raw),
        .video_on_raw(video_on_raw),
        .h_count_d(h_count_d),
        .v_count_d(v_count_d),
        .video_on_d(video_on_d),
        .x_vga(x_vga),
        .y_vga(y_vga),
        .tile_data(tile_data),
        .output_rgb(output_rgb)
    );

    task automatic check(input string name, input logic cond);
        if (cond) begin
            pass_count++;
            $display("PASS: %s", name);
        end else begin
            fail_count++;
            $display("FAIL: %s (rgb=%b x=%0d y=%0d)", name, output_rgb, x_vga, y_vga);
        end
    endtask

    // Screen pixel (hx, vy) maps to tile (hx[7:3], vy[7:3]+24)
    task automatic set_pixel(input int hx, input int vy, input logic [1:0] tile);
        h_count_raw = hx[9:0];
        v_count_raw = vy[9:0];
        h_count_d   = hx[9:0];
        v_count_d   = vy[9:0];
        video_on_raw = 1'b1;
        video_on_d   = 1'b1;
        tile_data    = tile;
        map_loaded   = 1'b1;
    endtask

    initial begin
        pass_count   = 0;
        fail_count   = 0;
        map_loaded   = 1'b0;
        h_count_raw  = '0;
        v_count_raw  = '0;
        video_on_raw = 1'b0;
        h_count_d    = '0;
        v_count_d    = '0;
        video_on_d   = 1'b0;
        tile_data    = 2'b00;

        $dumpfile("waves/vga_draw_tile.vcd");
        $dumpvars(0, vga_draw_tile_tb);

        #1;
        check("unloaded map black", output_rgb === 3'b000);

        // Tile (5,25): need v_count such that v[7:3]+24 = 25 => v[7:3]=1 => v in [8,15]
        // h in [40,47] => tile_x = 5
        set_pixel(40, 8, 2'b01);
        #1;
        check("request tile coords", (x_vga === 5'd5) && (y_vga === 5'd25));
        check("wall tile blue", output_rgb === 3'b001);

        set_pixel(40, 8, 2'b00);
        #1;
        check("empty tile black", output_rgb === 3'b000);

        // Pellet lit only at local pixels (3,3)/(3,4)/(4,3)/(4,4)
        set_pixel(40 + 3, 8 + 3, 2'b10);
        #1;
        check("pellet center white", output_rgb === 3'b111);

        set_pixel(40 + 0, 8 + 0, 2'b10);
        #1;
        check("pellet corner black", output_rgb === 3'b000);

        // Power pellet interior white (e.g. pixel 2,2), corners cut out
        set_pixel(40 + 2, 8 + 2, 2'b11);
        #1;
        check("power pellet body white", output_rgb === 3'b111);

        set_pixel(40 + 1, 8 + 1, 2'b11);
        #1;
        check("power pellet cut corner black", output_rgb === 3'b000);

        video_on_d = 1'b0;
        set_pixel(40, 8, 2'b01);
        video_on_d = 1'b0;
        #1;
        check("video_off forces black", output_rgb === 3'b000);

        // Outside map horizontally (tile_x >= 28): h >= 224
        video_on_raw = 1'b1;
        video_on_d   = 1'b1;
        h_count_raw  = 10'd224;
        v_count_raw  = 10'd8;
        h_count_d    = 10'd224;
        v_count_d    = 10'd8;
        map_loaded   = 1'b1;
        tile_data    = 2'b01;
        #1;
        check("oob request defaults x/y", (x_vga === 5'd0) && (y_vga === 5'd0));
        check("oob draw black", output_rgb === 3'b000);

        $display("\nvga_draw_tile_tb: %0d PASS, %0d FAIL", pass_count, fail_count);
        $finish;
    end

endmodule

Pacman_FPGA/waves/vga_draw_tile.vcd
$date
	Sat Aug  1 00:16:17 2026
$end
$version
	Icarus Verilog
$end
$timescale
	1ps
$end
$scope module vga_draw_tile_tb $end
$var wire 5 ! y_vga [4:0] $end
$var wire 5 " x_vga [4:0] $end
$var wire 3 # output_rgb [2:0] $end
$var reg 10 $ h_count_d [9:0] $end
$var reg 10 % h_count_raw [9:0] $end
$var reg 1 & map_loaded $end
$var reg 2 ' tile_data [1:0] $end
$var reg 10 ( v_count_d [9:0] $end
$var reg 10 ) v_count_raw [9:0] $end
$var reg 1 * video_on_d $end
$var reg 1 + video_on_raw $end
$var integer 32 , fail_count [31:0] $end
$var integer 32 - pass_count [31:0] $end
$scope module dut $end
$var wire 10 . h_count_d [9:0] $end
$var wire 10 / h_count_raw [9:0] $end
$var wire 1 0 in_map_d $end
$var wire 1 1 in_map_raw $end
$var wire 1 & map_loaded $end
$var wire 2 2 tile_data [1:0] $end
$var wire 10 3 v_count_d [9:0] $end
$var wire 10 4 v_count_raw [9:0] $end
$var wire 1 * video_on_d $end
$var wire 1 + video_on_raw $end
$var wire 5 5 tile_y_raw [4:0] $end
$var wire 5 6 tile_x_raw [4:0] $end
$var wire 3 7 pixel_y_d [2:0] $end
$var wire 3 8 pixel_x_d [2:0] $end
$var reg 3 9 output_rgb [2:0] $end
$var reg 5 : x_vga [4:0] $end
$var reg 5 ; y_vga [4:0] $end
$upscope $end
$scope task check $end
$upscope $end
$scope task set_pixel $end
$upscope $end
$upscope $end
$enddefinitions $end
$comment Show the parameter values. $end
$dumpall
$end
#0
$dumpvars
b0 ;
b0 :
b0 9
b0 8
b0 7
b0 6
b11000 5
b0 4
b0 3
b0 2
01
00
b0 /
b0 .
b0 -
b0 ,
0+
0*
b0 )
b0 (
b0 '
0&
b0 %
b0 $
b0 #
b0 "
b0 !
$end
#1000
b1 #
b1 9
b11001 !
b11001 ;
b101 "
b101 :
10
11
b11001 5
b101 6
1&
b1 '
b1 2
1*
1+
b1000 (
b1000 3
b101000 $
b101000 .
b1000 )
b1000 4
b101000 %
b101000 /
b1 -
#2000
b0 #
b0 9
b0 '
b0 2
b11 -
#3000
b111 #
b111 9
b11 7
b11 8
b10 '
b10 2
b1011 (
b1011 3
b101011 $
b101011 .
b1011 )
b1011 4
b101011 %
b101011 /
b100 -
#4000
b0 #
b0 9
b0 7
b0 8
b1000 (
b1000 3
b101000 $
b101000 .
b1000 )
b1000 4
b101000 %
b101000 /
b101 -
#5000
b111 #
b111 9
b10 7
b10 8
b11 '
b11 2
b1010 (
b1010 3
b101010 $
b101010 .
b1010 )
b1010 4
b101010 %
b101010 /
b110 -
#6000
b0 #
b0 9
b1 7
b1 8
b1001 (
b1001 3
b101001 $
b101001 .
b1001 )
b1001 4
b101001 %
b101001 /
b111 -
#7000
00
b0 7
b0 8
b1 '
b1 2
b1000 (
b1000 3
b101000 $
b101000 .
b1000 )
b1000 4
b101000 %
b101000 /
0*
b1000 -
#8000
b0 !
b0 ;
01
b0 #
b0 9
b0 "
b0 :
00
b11100 6
b11100000 $
b11100000 .
b11100000 %
b11100000 /
1*
b1001 -
#9000
b1011 -
