Pacman_FPGA/source/vga_draw_border.sv
module vga_draw_border(
    input logic  [9:0] h_count,    //Horizontal Display Counter (max value is 640px)
    input logic  [9:0] v_count,    //Vertical Display Counter (maxvalue is 480px)
    input logic        video_on,   //video on signal from vga_counter
    input logic  [2:0] input_rgb,  //pixel color from draw_sprite
    output logic [2:0] output_rgb  //pixel color
  );
  //variables
    logic black_right, black_bottom, black_top, black_top_between_numbers;


  //determine whether pixel is in the map
  assign black_right               = ((h_count >= 224));
  assign black_bottom              = ((v_count >= (288+24+8)) && (v_count < 480));
  assign black_top_between_numbers = ((v_count < 8)  && (h_count == 0 || (h_count > 39 && h_count < 48) || (h_count >= 72)));
  assign black_top                 = ((v_count < 64) && (v_count > 7 )  ||  black_top_between_numbers);

  //pixel generator for tile
  always_comb begin
    //draw black if not on map
    if (~video_on)
      output_rgb = 3'b000;
    else if (black_right)
      output_rgb = 3'b000;
    else if (black_bottom)
      output_rgb = 3'b000;
    else if (black_top)
      output_rgb = 3'b000;
    //draw blue wall if applicable
    else
      output_rgb = input_rgb;
  end
endmodule

Pacman_FPGA/testbench/vga_draw_border_tb.sv
`timescale 1ns/1ps

module vga_draw_border_tb;

    logic [9:0] h_count;
    logic [9:0] v_count;
    logic       video_on;
    logic [2:0] input_rgb;
    logic [2:0] output_rgb;

    int pass_count;
    int fail_count;

    vga_draw_border dut (
        .h_count(h_count),
        .v_count(v_count),
        .video_on(video_on),
        .input_rgb(input_rgb),
        .output_rgb(output_rgb)
    );

    task automatic check(input string name, input logic cond);
        if (cond) begin
            pass_count++;
            $display("PASS: %s", name);
        end else begin
            fail_count++;
            $display("FAIL: %s (out=%b)", name, output_rgb);
        end
    endtask

    initial begin
        pass_count = 0;
        fail_count = 0;
        h_count    = 10'd100;
        v_count    = 10'd100;
        video_on   = 1'b1;
        input_rgb  = 3'b101;

        $dumpfile("waves/vga_draw_border.vcd");
        $dumpvars(0, vga_draw_border_tb);

        #1;
        check("pass-through in playfield", output_rgb === 3'b101);

        video_on = 1'b0;
        #1;
        check("blank when video_off", output_rgb === 3'b000);

        video_on = 1'b1;
        h_count  = 10'd224;
        v_count  = 10'd100;
        #1;
        check("black right margin", output_rgb === 3'b000);

        h_count = 10'd100;
        v_count = 10'd320; // >= 288+24+8 = 320
        #1;
        check("black bottom margin", output_rgb === 3'b000);

        v_count = 10'd32; // between 8 and 64
        #1;
        check("black top band", output_rgb === 3'b000);

        // Score row gaps: v<8 and h in gap regions
        v_count = 10'd3;
        h_count = 10'd0;
        #1;
        check("black between score glyphs h=0", output_rgb === 3'b000);

        h_count = 10'd45;
        #1;
        check("black between score glyphs gap", output_rgb === 3'b000);

        h_count = 10'd80;
        #1;
        check("black right of score row", output_rgb === 3'b000);

        // Inside SCORE letter strip should pass through (h=4, v=3)
        h_count = 10'd4;
        v_count = 10'd3;
        input_rgb = 3'b111;
        #1;
        check("score letter strip pass-through", output_rgb === 3'b111);

        $display("\nvga_draw_border_tb: %0d PASS, %0d FAIL", pass_count, fail_count);
        $finish;
    end

endmodule

Pacman_FPGA/waves/vga_draw_border.vcd
$date
	Sat Aug  1 00:16:17 2026
$end
$version
	Icarus Verilog
$end
$timescale
	1ps
$end
$scope module vga_draw_border_tb $end
$var wire 3 ! output_rgb [2:0] $end
$var reg 10 " h_count [9:0] $end
$var reg 3 # input_rgb [2:0] $end
$var reg 10 $ v_count [9:0] $end
$var reg 1 % video_on $end
$var integer 32 & fail_count [31:0] $end
$var integer 32 ' pass_count [31:0] $end
$scope module dut $end
$var wire 1 ( black_bottom $end
$var wire 1 ) black_top $end
$var wire 1 * black_top_between_numbers $end
$var wire 10 + h_count [9:0] $end
$var wire 3 , input_rgb [2:0] $end
$var wire 10 - v_count [9:0] $end
$var wire 1 % video_on $end
$var wire 1 . black_right $end
$var reg 3 / output_rgb [2:0] $end
$upscope $end
$scope task check $end
$upscope $end
$upscope $end
$enddefinitions $end
$comment Show the parameter values. $end
$dumpall
$end
#0
$dumpvars
b101 /
0.
b1100100 -
b101 ,
b1100100 +
0*
0)
0(
b0 '
b0 &
1%
b1100100 $
b101 #
b1100100 "
b101 !
$end
#1000
b0 !
b0 /
0%
b1 '
#2000
1.
b11100000 "
b11100000 +
1%
b10 '
#3000
1(
b0 !
b0 /
b101000000 $
b101000000 -
0.
b1100100 "
b1100100 +
b11 '
#4000
1)
0(
b100000 $
b100000 -
b100 '
#5000
b0 !
b0 /
1)
1*
b0 "
b0 +
b11 $
b11 -
b101 '
#6000
b101101 "
b101101 +
b110 '
#7000
b1010000 "
b1010000 +
b111 '
#8000
b111 !
b111 /
0)
0*
b111 #
b111 ,
b100 "
b100 +
b1000 '
#9000
b1001 '
